<?xml version="1.0" encoding="utf-8"?>
<Defs>
	<KCSG.StructureLayoutDef>
		<defName>AP_Prefab_Production_1</defName>
		<spawnConduits>false</spawnConduits>
		<layouts>
			<li>
				<li>.,.,.,.,.,PowerConduit,.,.,.,.,.,.,.,.,.,.,.,.,.,.</li>
				<li>.,.,Wall_Steel,Wall_Steel,Wall_Steel,Wall_Steel,Wall_Steel,Wall_Steel,Wall_Steel,.,.,Wall_Steel,Wall_Steel,Wall_Steel,Wall_Steel,Wall_Steel,Wall_Steel,Wall_Steel,.,.</li>
				<li>.,.,Wall_Steel,.,.,.,.,.,Wall_Steel,Autodoor_Steel,Autodoor_Steel,Wall_Steel,.,.,.,.,.,Wall_Steel,.,.</li>
				<li>.,.,Wall_Steel,.,.,FabricationBench_South,.,.,Wall_Steel,.,.,Wall_Steel,.,.,VFE_TableMachiningLarge_South,.,.,Wall_Steel,.,.</li>
				<li>.,.,Wall_Steel,.,VFE_FabricationCabinet_South,DiningChair_WoodLog_South,.,VFE_FabricationCabinet_South,Wall_Steel,.,.,Wall_Steel,.,VFE_MachiningCabinet_South,DiningChair_WoodLog_South,.,VFE_MachiningCabinet_South,Wall_Steel,.,.</li>
				<li>.,.,Wall_Steel,.,.,.,.,.,PowerConduit,.,.,PowerConduit,.,.,.,ShelfSmall_Steel_West,.,Wall_Steel,.,.</li>
				<li>.,Wall_Steel,Wall_Steel,Shelf_Steel_East,StandingLamp,.,ShelfSmall_Steel_South,DiningChair_WoodLog_North,ShelfSmall_Steel_South,.,.,PowerConduit,DiningChair_WoodLog_North,ShelfSmall_Steel_South,.,StandingLamp,PowerConduit,Wall_Steel,Wall_Steel,.</li>
				<li>.,Wall_Steel,PowerConduit,PowerConduit,PowerConduit,PowerConduit,PowerConduit,PowerConduit,PowerConduit,PowerConduit,PowerConduit,PowerConduit,PowerConduit,PowerConduit,PowerConduit,PowerConduit,PowerConduit,.,Wall_Steel,.</li>
				<li>.,Wall_Steel,.,BiofuelRefinery_West,DiningChair_WoodLog_West,.,.,.,.,.,.,.,.,.,.,.,DiningChair_WoodLog_East,VFE_TableDrugLabElectric_Steel_East,Wall_Steel,.</li>
				<li>.,Wall_Steel,.,.,.,.,Shelf_Steel_South,.,Shelf_Steel_South,.,Shelf_Steel_South,.,Shelf_Steel_South,.,Shelf_Steel_South,.,FirefoamPopper,.,Wall_Steel,.</li>
				<li>.,Wall_Steel,.,.,.,Shelf_Steel_North,.,Shelf_Steel_North,.,Shelf_Steel_North,.,Shelf_Steel_North,.,Shelf_Steel_North,.,.,FirefoamPopper,.,Wall_Steel,.</li>
				<li>.,Wall_Steel,.,BiofuelRefinery_West,DiningChair_WoodLog_West,.,.,.,.,.,.,.,.,.,.,.,DiningChair_WoodLog_East,VFE_TableDrugLabElectric_Steel_East,Wall_Steel,.</li>
				<li>.,Wall_Steel,PowerConduit,PowerConduit,PowerConduit,PowerConduit,PowerConduit,PowerConduit,PowerConduit,PowerConduit,PowerConduit,PowerConduit,PowerConduit,PowerConduit,PowerConduit,PowerConduit,PowerConduit,.,Wall_Steel,.</li>
				<li>.,Wall_Steel,Wall_Steel,ToolCabinet_West,StandingLamp,.,ShelfSmall_Steel_North,.,PowerConduit,.,.,PowerConduit,.,ShelfSmall_Steel_North,.,StandingLamp,PowerConduit,Wall_Steel,Wall_Steel,.</li>
				<li>.,.,Wall_Steel,.,.,.,.,.,PowerConduit,.,.,PowerConduit,.,.,.,ShelfSmall_Steel_West,ToolCabinet_East,Wall_Steel,.,.</li>
				<li>.,.,Wall_Steel,VFE_SmithyCabinet_North,.,DiningChair_WoodLog_North,VFE_SmithyCabinet_North,.,Wall_Steel,.,.,Wall_Steel,VFE_TailorCabinet_North,.,DiningChair_WoodLog_North,VFE_TailorCabinet_North,.,Wall_Steel,.,.</li>
				<li>.,.,Wall_Steel,.,.,VFE_TableSmithyLarge_North,.,.,Wall_Steel,.,.,Wall_Steel,.,.,VFE_TableTailorLarge_Steel_North,.,.,Wall_Steel,.,.</li>
				<li>.,.,Wall_Steel,.,.,.,.,.,Wall_Steel,Autodoor_Steel,Autodoor_Steel,Wall_Steel,.,.,.,.,.,Wall_Steel,.,.</li>
				<li>.,.,Wall_Steel,Wall_Steel,Wall_Steel,Wall_Steel,Wall_Steel,Wall_Steel,Wall_Steel,.,.,Wall_Steel,Wall_Steel,Wall_Steel,Wall_Steel,Wall_Steel,Wall_Steel,Wall_Steel,.,.</li>
				<li>.,.,.,.,.,.,.,.,.,.,.,.,.,.,.,.,.,.,.,.</li>
			</li>
			<li>
				<li>.,.,.,.,.,.,.,.,.,.,.,.,.,.,.,.,.,.,.,.</li>
				<li>.,.,PowerConduit,PowerConduit,PowerConduit,PowerConduit,PowerConduit,PowerConduit,PowerConduit,.,.,PowerConduit,PowerConduit,PowerConduit,PowerConduit,PowerConduit,PowerConduit,PowerConduit,.,.</li>
				<li>.,.,PowerConduit,.,.,.,.,.,PowerConduit,PowerConduit,PowerConduit,PowerConduit,.,.,.,.,.,PowerConduit,.,.</li>
				<li>.,.,PowerConduit,.,.,.,.,.,PowerConduit,.,.,PowerConduit,.,.,.,.,.,PowerConduit,.,.</li>
				<li>.,.,PowerConduit,.,.,.,.,.,PowerConduit,.,.,PowerConduit,.,.,.,.,.,PowerConduit,.,.</li>
				<li>.,.,PowerConduit,.,.,.,.,.,.,.,.,.,.,.,.,.,.,PowerConduit,.,.</li>
				<li>.,PowerConduit,PowerConduit,.,.,.,.,.,PowerConduit,.,.,ShelfSmall_Steel_South,.,.,.,.,ToolCabinet_East,PowerConduit,PowerConduit,.</li>
				<li>.,PowerConduit,.,.,FirefoamPopper,.,.,VFE_TableStonecutterElectric_Steel_North,.,Column_Steel,.,.,ElectricSmelter_North,.,.,.,VFE_DrugCabinet_South,.,PowerConduit,.</li>
				<li>.,PowerConduit,.,.,.,.,.,.,.,.,.,.,.,.,.,.,.,.,PowerConduit,.</li>
				<li>.,PowerConduit,.,.,.,.,.,.,.,.,.,.,.,.,.,.,.,.,PowerConduit,.</li>
				<li>.,PowerConduit,.,.,.,.,.,.,.,.,.,.,.,.,.,.,.,.,PowerConduit,.</li>
				<li>.,PowerConduit,.,.,.,.,.,.,.,.,.,.,.,.,.,.,.,.,PowerConduit,.</li>
				<li>.,PowerConduit,.,.,FirefoamPopper,.,.,VFE_TableStonecutterElectric_Steel_South,.,.,.,.,ElectricSmelter_South,.,.,.,VFE_DrugCabinet_South,.,PowerConduit,.</li>
				<li>.,PowerConduit,PowerConduit,.,.,.,.,.,ShelfSmall_Steel_North,.,.,ShelfSmall_Steel_North,.,.,.,.,.,PowerConduit,PowerConduit,.</li>
				<li>.,.,PowerConduit,.,.,.,.,.,.,.,.,.,.,.,.,.,.,PowerConduit,.,.</li>
				<li>.,.,PowerConduit,.,.,.,.,.,PowerConduit,.,.,PowerConduit,.,.,.,.,.,PowerConduit,.,.</li>
				<li>.,.,PowerConduit,.,.,.,.,.,PowerConduit,.,.,PowerConduit,.,.,.,.,.,PowerConduit,.,.</li>
				<li>.,.,PowerConduit,.,.,.,.,.,PowerConduit,PowerConduit,PowerConduit,PowerConduit,.,.,.,.,.,PowerConduit,.,.</li>
				<li>.,.,PowerConduit,PowerConduit,PowerConduit,PowerConduit,PowerConduit,PowerConduit,PowerConduit,.,.,PowerConduit,PowerConduit,PowerConduit,PowerConduit,PowerConduit,PowerConduit,PowerConduit,.,.</li>
				<li>.,.,.,.,.,.,.,.,.,.,.,.,.,.,.,.,.,.,.,.</li>
			</li>
		</layouts>
		<roofGrid>
			<li>.,.,.,.,.,.,.,.,.,.,.,.,.,.,.,.,.,.,.,.</li>
			<li>.,.,1,1,1,1,1,1,1,.,.,1,1,1,1,1,1,1,.,.</li>
			<li>.,.,1,1,1,1,1,1,1,1,1,1,1,1,1,1,1,1,.,.</li>
			<li>.,.,1,1,1,1,1,1,1,1,1,1,1,1,1,1,1,1,.,.</li>
			<li>.,.,1,1,1,1,1,1,1,1,1,1,1,1,1,1,1,1,.,.</li>
			<li>.,.,1,1,1,1,1,1,1,1,1,1,1,1,1,1,1,1,.,.</li>
			<li>.,1,1,1,1,1,1,1,1,1,1,1,1,1,1,1,1,1,1,.</li>
			<li>.,1,1,1,1,1,1,1,1,1,1,1,1,1,1,1,1,1,1,.</li>
			<li>.,1,1,1,1,1,1,1,1,1,1,1,1,1,1,1,1,1,1,.</li>
			<li>.,1,1,1,1,1,1,1,1,1,1,1,1,1,1,1,1,1,1,.</li>
			<li>.,1,1,1,1,1,1,1,1,1,1,1,1,1,1,1,1,1,1,.</li>
			<li>.,1,1,1,1,1,1,1,1,1,1,1,1,1,1,1,1,1,1,.</li>
			<li>.,1,1,1,1,1,1,1,1,1,1,1,1,1,1,1,1,1,1,.</li>
			<li>.,1,1,1,1,1,1,1,1,1,1,1,1,1,1,1,1,1,1,.</li>
			<li>.,.,1,1,1,1,1,1,1,1,1,1,1,1,1,1,1,1,.,.</li>
			<li>.,.,1,1,1,1,1,1,1,1,1,1,1,1,1,1,1,1,.,.</li>
			<li>.,.,1,1,1,1,1,1,1,1,1,1,1,1,1,1,1,1,.,.</li>
			<li>.,.,1,1,1,1,1,1,1,1,1,1,1,1,1,1,1,1,.,.</li>
			<li>.,.,1,1,1,1,1,1,1,.,.,1,1,1,1,1,1,1,.,.</li>
			<li>.,.,.,.,.,.,.,.,.,.,.,.,.,.,.,.,.,.,.,.</li>
		</roofGrid>
		<terrainGrid>
			<li>.,PavedTile,PavedTile,PavedTile,PavedTile,PavedTile,PavedTile,PavedTile,PavedTile,MetalTile,MetalTile,PavedTile,PavedTile,PavedTile,PavedTile,PavedTile,PavedTile,PavedTile,PavedTile,.</li>
			<li>.,PavedTile,.,.,.,.,.,.,.,MetalTile,MetalTile,.,.,.,.,.,.,.,PavedTile,.</li>
			<li>.,PavedTile,.,MetalTile,MetalTile,MetalTile,MetalTile,MetalTile,.,MetalTile,MetalTile,.,MetalTile,MetalTile,MetalTile,MetalTile,MetalTile,.,PavedTile,.</li>
			<li>.,PavedTile,.,MetalTile,PavedTile,PavedTile,PavedTile,MetalTile,.,MetalTile,MetalTile,.,MetalTile,PavedTile,PavedTile,PavedTile,MetalTile,.,PavedTile,.</li>
			<li>.,PavedTile,.,MetalTile,PavedTile,PavedTile,PavedTile,MetalTile,MetalTile,MetalTile,MetalTile,MetalTile,MetalTile,PavedTile,PavedTile,PavedTile,MetalTile,.,PavedTile,.</li>
			<li>PavedTile,PavedTile,.,MetalTile,PavedTile,PavedTile,PavedTile,MetalTile,MetalTile,MetalTile,MetalTile,MetalTile,MetalTile,PavedTile,PavedTile,PavedTile,MetalTile,.,PavedTile,PavedTile</li>
			<li>PavedTile,.,.,MetalTile,PavedTile,PavedTile,PavedTile,MetalTile,MetalTile,MetalTile,MetalTile,MetalTile,MetalTile,PavedTile,PavedTile,PavedTile,MetalTile,.,.,PavedTile</li>
			<li>PavedTile,.,MetalTile,MetalTile,MetalTile,MetalTile,MetalTile,MetalTile,MetalTile,MetalTile,MetalTile,MetalTile,MetalTile,MetalTile,MetalTile,MetalTile,MetalTile,MetalTile,.,PavedTile</li>
			<li>PavedTile,.,MetalTile,MetalTile,MetalTile,MetalTile,MetalTile,MetalTile,MetalTile,MetalTile,MetalTile,MetalTile,MetalTile,MetalTile,MetalTile,MetalTile,MetalTile,MetalTile,.,PavedTile</li>
			<li>PavedTile,.,MetalTile,MetalTile,MetalTile,MetalTile,MetalTile,MetalTile,MetalTile,MetalTile,MetalTile,MetalTile,MetalTile,MetalTile,MetalTile,MetalTile,MetalTile,MetalTile,.,PavedTile</li>
			<li>PavedTile,.,MetalTile,MetalTile,MetalTile,MetalTile,MetalTile,MetalTile,MetalTile,MetalTile,MetalTile,MetalTile,MetalTile,MetalTile,MetalTile,MetalTile,MetalTile,MetalTile,.,PavedTile</li>
			<li>PavedTile,.,MetalTile,MetalTile,MetalTile,MetalTile,MetalTile,MetalTile,MetalTile,MetalTile,MetalTile,MetalTile,MetalTile,MetalTile,MetalTile,MetalTile,MetalTile,MetalTile,.,PavedTile</li>
			<li>PavedTile,.,MetalTile,MetalTile,MetalTile,MetalTile,MetalTile,MetalTile,MetalTile,MetalTile,MetalTile,MetalTile,MetalTile,MetalTile,MetalTile,MetalTile,MetalTile,MetalTile,.,PavedTile</li>
			<li>PavedTile,.,.,MetalTile,PavedTile,PavedTile,PavedTile,MetalTile,MetalTile,MetalTile,MetalTile,MetalTile,MetalTile,PavedTile,PavedTile,PavedTile,MetalTile,.,.,PavedTile</li>
			<li>PavedTile,PavedTile,.,MetalTile,PavedTile,PavedTile,PavedTile,MetalTile,MetalTile,MetalTile,MetalTile,MetalTile,MetalTile,PavedTile,PavedTile,PavedTile,MetalTile,.,PavedTile,PavedTile</li>
			<li>.,PavedTile,.,MetalTile,PavedTile,PavedTile,PavedTile,MetalTile,MetalTile,MetalTile,MetalTile,MetalTile,MetalTile,PavedTile,PavedTile,PavedTile,MetalTile,.,PavedTile,.</li>
			<li>.,PavedTile,.,MetalTile,PavedTile,PavedTile,PavedTile,MetalTile,.,MetalTile,MetalTile,.,MetalTile,PavedTile,PavedTile,PavedTile,MetalTile,.,PavedTile,.</li>
			<li>.,PavedTile,.,MetalTile,MetalTile,MetalTile,MetalTile,MetalTile,.,MetalTile,MetalTile,.,MetalTile,MetalTile,MetalTile,MetalTile,MetalTile,.,PavedTile,.</li>
			<li>.,PavedTile,.,.,.,.,.,.,.,MetalTile,MetalTile,.,.,.,.,.,.,.,PavedTile,.</li>
			<li>.,PavedTile,PavedTile,PavedTile,PavedTile,PavedTile,PavedTile,PavedTile,PavedTile,MetalTile,MetalTile,PavedTile,PavedTile,PavedTile,PavedTile,PavedTile,PavedTile,PavedTile,PavedTile,.</li>
		</terrainGrid>
		<modRequirements>
			<li>vanillaexpanded.vfeproduction</li>
		</modRequirements>
	</KCSG.StructureLayoutDef>
	<KCSG.StructureLayoutDef>
		<defName>AP_Prefab_Production_Factory_1</defName>
		<spawnConduits>false</spawnConduits>
		<layouts>
			<li>
				<li>.,.,.,.,.,.,.,Fence_Steel,Fence_Steel,Fence_Steel,Fence_Steel,Fence_Steel,Fence_Steel,Fence_Steel,Fence_Steel,Fence_Steel,Fence_Steel,Fence_Steel,StandingLamp,.</li>
				<li>.,StandingLamp,Wall_Steel,Autodoor_Steel,Wall_Steel,Wall_Steel,.,.,.,.,.,.,.,.,.,.,.,.,.,.</li>
				<li>.,Wall_Steel,Wall_Steel,.,Battery_North,Wall_Steel,Wall_Steel,Wall_Steel,Wall_Steel,Wall_Steel,Wall_Steel,Wall_Steel,Wall_Steel,Wall_Steel,Wall_Steel,Wall_Steel,Wall_Steel,Wall_Steel,Wall_Steel,.</li>
				<li>.,Wall_Steel,.,.,.,Shelf_Steel_North,.,Shelf_Steel_North,.,PowerConduit,.,Shelf_Steel_North,.,Shelf_Steel_North,PowerConduit,Shelf_Steel_North,.,Battery_North,Wall_Steel,.</li>
				<li>.,Wall_Steel,Shelf_Steel_East,.,.,.,.,.,.,PowerConduit,.,.,.,.,PowerConduit,.,.,.,Wall_Steel,.</li>
				<li>.,Wall_Steel,.,.,.,.,VFEM_HeavyHopper_North,.,.,PowerConduit,.,VFEM_HeavyHopper_North,.,.,PowerConduit,.,VFEM_HeavyHopper_North,.,Wall_Steel,.</li>
				<li>.,Wall_Steel,Shelf_Steel_East,.,.,.,.,.,.,PowerConduit,.,.,.,.,PowerConduit,.,.,.,Wall_Steel,.</li>
				<li>.,Wall_Steel,.,.,.,.,.,.,.,PowerConduit,.,.,.,.,PowerConduit,.,.,.,Wall_Steel,.</li>
				<li>.,Wall_Steel,TableMachining_West,.,.,.,VFEM_ElectronicsFabricationFactory_SteelExtractor_North,.,.,PowerConduit,.,VFEM_ElectronicsFabricationFactory_SteelExtractor_North,.,.,PowerConduit,.,VFEM_ElectronicsFabricationFactory_SteelExtractor_North,.,Wall_Steel,.</li>
				<li>.,Wall_Steel,.,.,.,.,.,.,.,PowerConduit,.,.,.,.,PowerConduit,.,.,.,Wall_Steel,.</li>
				<li>.,Wall_Steel,ToolCabinet_West,.,VFE_MechanoidConstructionLamp,.,.,.,.,PowerConduit,.,.,.,.,PowerConduit,.,.,.,Wall_Steel,.</li>
				<li>.,Wall_Steel,PowerConduit,PowerConduit,PowerConduit,PowerConduit,PowerConduit,PowerConduit,PowerConduit,PowerConduit,PowerConduit,PowerConduit,PowerConduit,PowerConduit,PowerConduit,PowerConduit,PowerConduit,PowerConduit,Wall_Steel,.</li>
				<li>.,Wall_Steel,Wall_Steel,Battery_North,.,ChunkLimestone,ChunkSandstone,VFEM_HeavyHopper_South,.,PowerConduit,ChunkMarble,ChunkGranite,VFEM_HeavyHopper_South,.,PowerConduit,ChunkMarble,ChunkSandstone,VFEM_HeavyHopper_South,Wall_Steel,.</li>
				<li>.,.,Wall_Steel,.,.,.,.,.,.,PowerConduit,.,.,.,.,PowerConduit,.,.,.,Wall_Steel,.</li>
				<li>Fence_Steel,.,Wall_Steel,Battery_North,.,.,VFEM_MasonryAndMetallicsFactory_AutomaticDrill_North,.,.,PowerConduit,.,VFEM_MasonryAndMetallicsFactory_AutomaticDrill_North,.,.,PowerConduit,.,VFEM_MasonryAndMetallicsFactory_AutomaticDrill_North,.,Wall_Steel,.</li>
				<li>Fence_Steel,.,Wall_Steel,.,.,.,.,.,.,PowerConduit,.,.,.,.,PowerConduit,.,.,.,Wall_Steel,.</li>
				<li>Fence_Steel,.,Wall_Steel,Battery_North,.,.,.,.,.,PowerConduit,.,.,.,.,PowerConduit,.,.,.,Wall_Steel,.</li>
				<li>Fence_Steel,.,Wall_Steel,.,.,Wall_Steel,Wall_Steel,Wall_Steel,Wall_Steel,Wall_Steel,Wall_Steel,Wall_Steel,Wall_Steel,Wall_Steel,Wall_Steel,Wall_Steel,Wall_Steel,Wall_Steel,Wall_Steel,.</li>
				<li>Fence_Steel,.,Wall_Steel,Wall_Steel,Autodoor_Steel,Wall_Steel,.,.,.,.,.,.,.,.,.,.,.,.,.,.</li>
				<li>.,.,.,.,.,StandingLamp,.,Fence_Steel,Fence_Steel,Fence_Steel,Fence_Steel,Fence_Steel,Fence_Steel,Fence_Steel,Fence_Steel,Fence_Steel,Fence_Steel,Fence_Steel,StandingLamp,.</li>
			</li>
			<li>
				<li>.,.,.,.,.,.,.,.,.,.,.,.,.,.,.,.,.,.,.,.</li>
				<li>.,.,PowerConduit,PowerConduit,PowerConduit,PowerConduit,.,.,.,.,.,.,.,.,.,.,.,.,.,.</li>
				<li>.,PowerConduit,PowerConduit,.,.,PowerConduit,PowerConduit,PowerConduit,PowerConduit,PowerConduit,PowerConduit,PowerConduit,PowerConduit,PowerConduit,PowerConduit,PowerConduit,PowerConduit,PowerConduit,PowerConduit,.</li>
				<li>.,PowerConduit,.,.,.,.,.,.,.,Shelf_Steel_North,.,.,.,.,.,.,.,.,PowerConduit,.</li>
				<li>.,PowerConduit,.,.,.,.,.,.,.,.,.,.,.,.,.,.,.,.,PowerConduit,.</li>
				<li>.,PowerConduit,.,.,.,.,.,.,.,.,.,.,.,.,.,.,.,.,PowerConduit,.</li>
				<li>.,PowerConduit,.,.,.,.,.,.,.,.,.,.,.,.,.,.,.,.,PowerConduit,.</li>
				<li>.,PowerConduit,.,.,.,.,.,.,.,.,.,.,.,.,.,.,.,.,PowerConduit,.</li>
				<li>.,PowerConduit,.,.,.,.,.,.,.,.,.,.,.,.,.,.,.,.,PowerConduit,.</li>
				<li>.,PowerConduit,.,.,.,.,.,.,.,.,.,.,.,.,.,.,.,.,PowerConduit,.</li>
				<li>.,PowerConduit,.,.,.,.,.,.,.,.,.,.,.,.,VFE_MechanoidConstructionLamp,.,.,.,PowerConduit,.</li>
				<li>.,PowerConduit,.,.,.,.,.,.,.,.,.,.,.,.,.,.,.,.,PowerConduit,.</li>
				<li>.,PowerConduit,PowerConduit,.,.,VFEM_HeavyHopper_South,VFEM_HeavyHopper_South,.,.,.,VFEM_HeavyHopper_South,VFEM_HeavyHopper_South,.,.,.,VFEM_HeavyHopper_South,VFEM_HeavyHopper_South,.,PowerConduit,.</li>
				<li>.,.,PowerConduit,.,.,.,.,.,.,.,.,.,.,.,.,.,.,.,PowerConduit,.</li>
				<li>.,.,PowerConduit,.,.,.,.,.,.,.,.,.,.,.,.,.,.,.,PowerConduit,.</li>
				<li>.,.,PowerConduit,.,.,.,.,.,.,.,.,.,.,.,.,.,.,.,PowerConduit,.</li>
				<li>.,.,PowerConduit,.,.,.,.,.,.,.,.,.,.,.,.,.,.,.,PowerConduit,.</li>
				<li>.,.,PowerConduit,.,.,PowerConduit,PowerConduit,PowerConduit,PowerConduit,PowerConduit,PowerConduit,PowerConduit,PowerConduit,PowerConduit,PowerConduit,PowerConduit,PowerConduit,PowerConduit,PowerConduit,.</li>
				<li>.,.,PowerConduit,PowerConduit,PowerConduit,PowerConduit,.,.,.,.,.,.,.,.,.,.,.,.,.,.</li>
				<li>.,.,.,.,.,.,.,.,.,.,.,.,.,.,.,.,.,.,.,.</li>
			</li>
		</layouts>
		<roofGrid>
			<li>.,.,.,.,.,.,.,.,.,.,.,.,.,.,.,.,.,.,.,.</li>
			<li>.,.,1,1,1,1,.,.,.,.,.,.,.,.,.,.,.,.,.,.</li>
			<li>.,1,1,1,1,1,1,1,1,1,1,1,1,1,1,1,1,1,1,.</li>
			<li>.,1,1,1,1,1,1,1,1,1,1,1,1,1,1,1,1,1,1,.</li>
			<li>.,1,1,1,1,1,1,1,1,1,1,1,1,1,1,1,1,1,1,.</li>
			<li>.,1,1,1,1,1,1,1,1,1,1,1,1,1,1,1,1,1,1,.</li>
			<li>.,1,1,1,1,1,1,1,1,1,1,1,1,1,1,1,1,1,1,.</li>
			<li>.,1,1,1,1,1,1,1,1,1,1,1,1,1,1,1,1,1,1,.</li>
			<li>.,1,1,1,1,1,1,1,1,1,1,1,1,1,1,1,1,1,1,.</li>
			<li>.,1,1,1,1,1,1,1,1,1,1,1,1,1,1,1,1,1,1,.</li>
			<li>.,1,1,1,1,1,1,1,1,1,1,1,1,1,1,1,1,1,1,.</li>
			<li>.,1,1,1,1,1,1,1,1,1,1,1,1,1,1,1,1,1,1,.</li>
			<li>.,1,1,1,1,1,1,1,1,1,1,1,1,1,1,1,1,1,1,.</li>
			<li>.,.,1,1,1,1,1,1,1,1,1,1,1,1,1,1,1,1,1,.</li>
			<li>.,.,1,1,1,1,1,1,1,1,1,1,1,1,1,1,1,1,1,.</li>
			<li>.,.,1,1,1,1,1,1,1,1,1,1,1,1,1,1,1,1,1,.</li>
			<li>.,.,1,1,1,1,1,1,1,1,1,1,1,1,1,1,1,1,1,.</li>
			<li>.,.,1,1,1,1,1,1,1,1,1,1,1,1,1,1,1,1,1,.</li>
			<li>.,.,1,1,1,1,.,.,.,.,.,.,.,.,.,.,.,.,.,.</li>
			<li>.,.,.,.,.,.,.,.,.,.,.,.,.,.,.,.,.,.,.,.</li>
		</roofGrid>
		<terrainGrid>
			<li>.,PavedTile,PavedTile,PavedTile,PavedTile,PavedTile,PavedTile,PavedTile,PavedTile,PavedTile,PavedTile,PavedTile,PavedTile,PavedTile,PavedTile,PavedTile,PavedTile,PavedTile,PavedTile,.</li>
			<li>PavedTile,PavedTile,PavedTile,PavedTile,PavedTile,PavedTile,PavedTile,PavedTile,PavedTile,PavedTile,PavedTile,PavedTile,PavedTile,PavedTile,PavedTile,PavedTile,PavedTile,PavedTile,PavedTile,PavedTile</li>
			<li>PavedTile,PavedTile,PavedTile,PavedTile,PavedTile,PavedTile,PavedTile,PavedTile,PavedTile,PavedTile,PavedTile,PavedTile,PavedTile,PavedTile,PavedTile,PavedTile,PavedTile,PavedTile,PavedTile,PavedTile</li>
			<li>PavedTile,PavedTile,PavedTile,PavedTile,PavedTile,PavedTile,PavedTile,PavedTile,PavedTile,PavedTile,PavedTile,PavedTile,PavedTile,PavedTile,PavedTile,PavedTile,PavedTile,PavedTile,PavedTile,PavedTile</li>
			<li>PavedTile,PavedTile,PavedTile,PavedTile,VFE_FactoryPath,VFE_FactoryPath,VFE_FactoryPath,VFE_FactoryPath,VFE_FactoryPath,VFE_FactoryPath,VFE_FactoryPath,VFE_FactoryPath,VFE_FactoryPath,VFE_FactoryPath,VFE_FactoryPath,VFE_FactoryPath,VFE_FactoryPath,VFE_FactoryPath,PavedTile,PavedTile</li>
			<li>PavedTile,PavedTile,PavedTile,PavedTile,VFE_FactoryPath,VFE_FactoryFloor,VFE_FactoryFloor,VFE_FactoryFloor,VFE_FactoryPath,VFE_FactoryPath,VFE_FactoryFloor,VFE_FactoryFloor,VFE_FactoryFloor,VFE_FactoryPath,VFE_FactoryPath,VFE_FactoryFloor,VFE_FactoryFloor,VFE_FactoryFloor,PavedTile,PavedTile</li>
			<li>PavedTile,PavedTile,PavedTile,PavedTile,VFE_FactoryPath,VFE_FactoryFloor,VFE_FactoryFloor,VFE_FactoryFloor,VFE_FactoryPath,VFE_FactoryPath,VFE_FactoryFloor,VFE_FactoryFloor,VFE_FactoryFloor,VFE_FactoryPath,VFE_FactoryPath,VFE_FactoryFloor,VFE_FactoryFloor,VFE_FactoryFloor,PavedTile,PavedTile</li>
			<li>PavedTile,PavedTile,PavedTile,PavedTile,VFE_FactoryPath,VFE_FactoryFloor,VFE_FactoryFloor,VFE_FactoryFloor,VFE_FactoryPath,VFE_FactoryPath,VFE_FactoryFloor,VFE_FactoryFloor,VFE_FactoryFloor,VFE_FactoryPath,VFE_FactoryPath,VFE_FactoryFloor,VFE_FactoryFloor,VFE_FactoryFloor,PavedTile,PavedTile</li>
			<li>PavedTile,PavedTile,PavedTile,PavedTile,VFE_FactoryPath,VFE_FactoryFloor,VFE_FactoryFloor,VFE_FactoryFloor,VFE_FactoryPath,VFE_FactoryPath,VFE_FactoryFloor,VFE_FactoryFloor,VFE_FactoryFloor,VFE_FactoryPath,VFE_FactoryPath,VFE_FactoryFloor,VFE_FactoryFloor,VFE_FactoryFloor,PavedTile,PavedTile</li>
			<li>PavedTile,PavedTile,PavedTile,PavedTile,VFE_FactoryPath,VFE_FactoryFloor,VFE_FactoryFloor,VFE_FactoryFloor,VFE_FactoryPath,VFE_FactoryPath,VFE_FactoryFloor,VFE_FactoryFloor,VFE_FactoryFloor,VFE_FactoryPath,VFE_FactoryPath,VFE_FactoryFloor,VFE_FactoryFloor,VFE_FactoryFloor,PavedTile,PavedTile</li>
			<li>PavedTile,PavedTile,PavedTile,PavedTile,VFE_FactoryPath,VFE_FactoryFloor,VFE_FactoryFloor,VFE_FactoryFloor,VFE_FactoryPath,VFE_FactoryPath,VFE_FactoryFloor,VFE_FactoryFloor,VFE_FactoryFloor,VFE_FactoryPath,VFE_FactoryPath,VFE_FactoryFloor,VFE_FactoryFloor,VFE_FactoryFloor,PavedTile,PavedTile</li>
			<li>PavedTile,PavedTile,PavedTile,PavedTile,VFE_FactoryPath,VFE_FactoryFloor,VFE_FactoryFloor,VFE_FactoryFloor,VFE_FactoryPath,VFE_FactoryPath,VFE_FactoryFloor,VFE_FactoryFloor,VFE_FactoryFloor,VFE_FactoryPath,VFE_FactoryPath,VFE_FactoryFloor,VFE_FactoryFloor,VFE_FactoryFloor,PavedTile,PavedTile</li>
			<li>PavedTile,PavedTile,PavedTile,PavedTile,VFE_FactoryFloor,VFE_FactoryFloor,VFE_FactoryFloor,VFE_FactoryFloor,VFE_FactoryFloor,VFE_FactoryFloor,VFE_FactoryFloor,VFE_FactoryFloor,VFE_FactoryFloor,VFE_FactoryFloor,VFE_FactoryFloor,VFE_FactoryFloor,VFE_FactoryFloor,VFE_FactoryFloor,PavedTile,PavedTile</li>
			<li>PavedTile,PavedTile,PavedTile,PavedTile,VFE_FactoryPath,VFE_FactoryFloor,VFE_FactoryFloor,VFE_FactoryFloor,VFE_FactoryPath,VFE_FactoryPath,VFE_FactoryFloor,VFE_FactoryFloor,VFE_FactoryFloor,VFE_FactoryPath,VFE_FactoryPath,VFE_FactoryFloor,VFE_FactoryFloor,VFE_FactoryFloor,PavedTile,PavedTile</li>
			<li>PavedTile,PavedTile,PavedTile,PavedTile,VFE_FactoryPath,VFE_FactoryFloor,VFE_FactoryFloor,VFE_FactoryFloor,VFE_FactoryPath,VFE_FactoryPath,VFE_FactoryFloor,VFE_FactoryFloor,VFE_FactoryFloor,VFE_FactoryPath,VFE_FactoryPath,VFE_FactoryFloor,VFE_FactoryFloor,VFE_FactoryFloor,PavedTile,PavedTile</li>
			<li>PavedTile,PavedTile,PavedTile,PavedTile,VFE_FactoryPath,VFE_FactoryFloor,VFE_FactoryFloor,VFE_FactoryFloor,VFE_FactoryPath,VFE_FactoryPath,VFE_FactoryFloor,VFE_FactoryFloor,VFE_FactoryFloor,VFE_FactoryPath,VFE_FactoryPath,VFE_FactoryFloor,VFE_FactoryFloor,VFE_FactoryFloor,PavedTile,PavedTile</li>
			<li>PavedTile,PavedTile,PavedTile,PavedTile,VFE_FactoryPath,VFE_FactoryPath,VFE_FactoryPath,VFE_FactoryPath,VFE_FactoryPath,VFE_FactoryPath,VFE_FactoryPath,VFE_FactoryPath,VFE_FactoryPath,VFE_FactoryPath,VFE_FactoryPath,VFE_FactoryPath,VFE_FactoryPath,VFE_FactoryPath,PavedTile,PavedTile</li>
			<li>PavedTile,PavedTile,PavedTile,PavedTile,PavedTile,PavedTile,PavedTile,PavedTile,PavedTile,PavedTile,PavedTile,PavedTile,PavedTile,PavedTile,PavedTile,PavedTile,PavedTile,PavedTile,PavedTile,PavedTile</li>
			<li>PavedTile,PavedTile,.,.,PavedTile,.,PavedTile,PavedTile,PavedTile,PavedTile,PavedTile,PavedTile,PavedTile,PavedTile,PavedTile,PavedTile,PavedTile,PavedTile,PavedTile,PavedTile</li>
			<li>PavedTile,PavedTile,PavedTile,PavedTile,PavedTile,PavedTile,PavedTile,PavedTile,PavedTile,PavedTile,PavedTile,PavedTile,PavedTile,PavedTile,PavedTile,PavedTile,PavedTile,PavedTile,PavedTile,.</li>
		</terrainGrid>
		<modRequirements>
			<li>oskarpotocki.vfe.mechanoid</li>
		</modRequirements>
	</KCSG.StructureLayoutDef>
	<KCSG.StructureLayoutDef>
		<defName>AP_Prefab_Production_Factory_2</defName>
		<spawnConduits>false</spawnConduits>
		<layouts>
			<li>
				<li>.,Fence_Steel,Fence_Steel,Wall_Steel,Wall_Steel,Wall_Steel,Wall_Steel,Wall_Steel,Wall_Steel,Wall_Steel,Wall_Steel,Wall_Steel,Wall_Steel,Wall_Steel,Wall_Steel,Wall_Steel,Wall_Steel,Fence_Steel,Fence_Steel,.</li>
				<li>.,.,StandingLamp,Wall_Steel,Battery_East,.,Battery_East,.,Battery_East,.,Battery_East,.,Battery_East,.,Battery_East,.,Wall_Steel,StandingLamp,.,.</li>
				<li>.,.,.,Autodoor_Steel,.,.,.,.,.,PowerConduit,.,PowerConduit,.,.,.,.,Autodoor_Steel,.,.,.</li>
				<li>.,Wall_Steel,Wall_Steel,Wall_Steel,StandingLamp,.,.,.,.,PowerConduit,.,PowerConduit,.,.,.,StandingLamp,Wall_Steel,Wall_Steel,Fence_Steel,.</li>
				<li>.,Wall_Steel,.,.,.,.,.,.,VFEM_MasonryAndMetallicsFactory_AutomaticDrill_South,PowerConduit,.,PowerConduit,VFEM_MasonryAndMetallicsFactory_AutomaticDrill_South,.,.,.,Shelf_Steel_West,Wall_Steel,.,.</li>
				<li>.,Wall_Steel,.,.,.,.,.,.,.,PowerConduit,.,PowerConduit,.,.,.,.,.,Wall_Steel,.,.</li>
				<li>.,Wall_Steel,.,FabricationBench_West,.,.,.,VFEM_HeavyHopper_North,VFEM_HeavyHopper_North,VFEM_HeavyHopper_North,.,VFEM_HeavyHopper_North,VFEM_HeavyHopper_North,VFEM_HeavyHopper_North,.,.,Shelf_Steel_West,Wall_Steel,.,.</li>
				<li>.,Wall_Steel,.,.,.,.,.,.,.,PowerConduit,.,PowerConduit,.,.,.,.,.,Wall_Steel,.,.</li>
				<li>.,Wall_Steel,.,.,.,.,.,.,.,PowerConduit,.,PowerConduit,.,.,.,.,Shelf_Steel_West,Wall_Steel,.,.</li>
				<li>.,Wall_Steel,ToolCabinet_North,.,.,.,.,.,.,PowerConduit,.,PowerConduit,.,.,.,.,.,Wall_Steel,.,.</li>
				<li>.,Wall_Steel,.,.,.,.,.,.,VFEM_ElectronicsFabricationFactory_SteelExtractor_South,PowerConduit,VFE_MechanoidConstructionLamp,PowerConduit,VFEM_ElectronicsFabricationFactory_SteelExtractor_South,.,.,.,Shelf_Steel_West,Wall_Steel,.,.</li>
				<li>.,Wall_Steel,.,.,.,.,.,.,.,PowerConduit,.,PowerConduit,.,.,.,.,.,Wall_Steel,.,.</li>
				<li>.,Wall_Steel,.,FabricationBench_West,.,.,.,.,.,PowerConduit,.,PowerConduit,.,.,.,.,Shelf_Steel_West,Wall_Steel,.,.</li>
				<li>.,Wall_Steel,.,.,.,.,.,.,VFEM_HeavyHopper_North,PowerConduit,.,PowerConduit,VFEM_HeavyHopper_North,.,.,.,.,Wall_Steel,.,.</li>
				<li>.,PowerConduit,.,.,PowerConduit,PowerConduit,PowerConduit,PowerConduit,PowerConduit,PowerConduit,PowerConduit,PowerConduit,PowerConduit,PowerConduit,PowerConduit,PowerConduit,PowerConduit,PowerConduit,Fence_Steel,Fence_Steel</li>
				<li>Fence_Steel,Wall_Steel,Wall_Steel,Wall_Steel,Wall_Steel,.,.,.,.,.,.,.,.,.,.,.,Wall_Steel,StandingLamp,.,Fence_Steel</li>
				<li>Fence_Steel,.,.,StandingLamp,Wall_Steel,.,.,.,.,.,VFEM_ElectronicsFabricationFactory_ComponentAssembler_North,.,.,.,.,.,Wall_Steel,.,.,.</li>
				<li>.,.,.,.,PowerConduit,.,.,.,.,.,.,.,.,.,.,.,PowerConduit,.,.,.</li>
				<li>.,Fence_Steel,Fence_Steel,Fence_Steel,Wall_Steel,StandingLamp,.,.,.,.,.,.,.,.,.,StandingLamp,Wall_Steel,Fence_Steel,Fence_Steel,.</li>
				<li>.,.,.,.,Wall_Steel,.,.,.,.,.,VFEM_HeavyHopper_South,.,.,.,.,.,Wall_Steel,.,.,.</li>
				<li>.,.,.,.,Wall_Steel,ElectricSmelter_West,.,.,.,.,.,.,.,.,.,ElectricSmelter_East,Wall_Steel,.,.,.</li>
				<li>.,.,.,.,Wall_Steel,.,ShelfSmall_Steel_South,.,Shelf_Steel_South,.,.,.,.,Shelf_Steel_South,ShelfSmall_Steel_South,.,Wall_Steel,.,.,.</li>
				<li>.,.,.,.,Wall_Steel,Wall_Steel,Wall_Steel,Wall_Steel,Wall_Steel,.,.,.,Wall_Steel,Wall_Steel,Wall_Steel,Wall_Steel,Wall_Steel,.,.,.</li>
				<li>.,.,.,.,.,.,.,.,Wall_Steel,Autodoor_Steel,Wall_Steel,Autodoor_Steel,Wall_Steel,.,.,.,.,.,.,.</li>
				<li>.,.,.,.,.,.,.,.,Fence_Steel,.,StandingLamp,.,Fence_Steel,.,.,.,.,.,.,.</li>
			</li>
			<li>
				<li>.,.,.,PowerConduit,PowerConduit,PowerConduit,PowerConduit,PowerConduit,PowerConduit,PowerConduit,PowerConduit,PowerConduit,PowerConduit,PowerConduit,PowerConduit,PowerConduit,PowerConduit,.,.,.</li>
				<li>.,.,.,PowerConduit,.,.,.,.,.,.,.,.,.,.,.,.,PowerConduit,.,.,.</li>
				<li>.,.,.,PowerConduit,.,.,.,.,.,.,.,.,.,.,.,.,PowerConduit,.,.,.</li>
				<li>.,PowerConduit,PowerConduit,PowerConduit,.,.,.,.,.,.,.,.,.,.,.,.,PowerConduit,PowerConduit,.,.</li>
				<li>.,PowerConduit,.,.,.,.,.,.,.,.,.,.,.,.,.,.,.,PowerConduit,.,.</li>
				<li>.,PowerConduit,.,.,.,.,.,.,.,.,.,.,.,.,.,.,.,PowerConduit,.,.</li>
				<li>.,PowerConduit,.,.,.,.,.,.,.,PowerConduit,.,PowerConduit,.,.,.,.,.,PowerConduit,.,.</li>
				<li>.,PowerConduit,.,.,.,.,.,.,.,.,.,.,.,.,.,.,.,PowerConduit,.,.</li>
				<li>.,PowerConduit,.,.,.,.,.,.,.,.,.,.,.,.,.,.,.,PowerConduit,.,.</li>
				<li>.,PowerConduit,.,.,.,.,.,.,.,.,.,.,.,.,.,.,.,PowerConduit,.,.</li>
				<li>.,PowerConduit,.,.,.,.,.,.,.,.,.,.,.,.,.,.,.,PowerConduit,.,.</li>
				<li>.,PowerConduit,.,.,.,.,.,.,.,.,.,.,.,.,.,.,.,PowerConduit,.,.</li>
				<li>.,PowerConduit,.,.,.,.,.,.,.,.,.,.,.,.,.,.,.,PowerConduit,.,.</li>
				<li>.,PowerConduit,.,.,.,.,.,.,.,.,.,.,.,.,.,.,.,PowerConduit,.,.</li>
				<li>.,Wall_Steel,.,.,.,.,.,.,.,.,.,.,.,.,.,.,Wall_Steel,Wall_Steel,.,.</li>
				<li>.,PowerConduit,PowerConduit,PowerConduit,PowerConduit,.,.,.,.,.,.,.,.,.,.,.,PowerConduit,.,.,.</li>
				<li>.,.,.,.,PowerConduit,.,.,.,.,.,.,.,.,.,.,.,PowerConduit,.,.,.</li>
				<li>.,.,.,.,Autodoor_Steel,.,.,.,.,.,.,.,.,.,.,.,Autodoor_Steel,.,.,.</li>
				<li>.,.,.,.,PowerConduit,.,.,.,.,.,.,.,.,.,.,.,PowerConduit,.,.,.</li>
				<li>.,.,.,.,PowerConduit,.,.,.,.,.,.,.,.,.,.,.,PowerConduit,.,.,.</li>
				<li>.,.,.,.,PowerConduit,.,.,.,.,.,.,.,.,.,.,.,PowerConduit,.,.,.</li>
				<li>.,.,.,.,PowerConduit,.,.,.,.,.,.,.,.,.,.,.,PowerConduit,.,.,.</li>
				<li>.,.,.,.,PowerConduit,PowerConduit,PowerConduit,PowerConduit,PowerConduit,.,.,.,PowerConduit,PowerConduit,PowerConduit,PowerConduit,PowerConduit,.,.,.</li>
				<li>.,.,.,.,.,.,.,.,PowerConduit,PowerConduit,PowerConduit,PowerConduit,PowerConduit,.,.,.,.,.,.,.</li>
				<li>.,.,.,.,.,.,.,.,.,.,.,.,.,.,.,.,.,.,.,.</li>
			</li>
		</layouts>
		<roofGrid>
			<li>.,.,.,1,1,1,1,1,1,1,1,1,1,1,1,1,1,.,.,.</li>
			<li>.,.,.,1,1,1,1,1,1,1,1,1,1,1,1,1,1,.,.,.</li>
			<li>.,.,.,1,1,1,1,1,1,1,1,1,1,1,1,1,1,.,.,.</li>
			<li>.,1,1,1,1,1,1,1,1,1,1,1,1,1,1,1,1,1,.,.</li>
			<li>.,1,1,1,1,1,1,1,1,1,1,1,1,1,1,1,1,1,.,.</li>
			<li>.,1,1,1,1,1,1,1,1,1,1,1,1,1,1,1,1,1,.,.</li>
			<li>.,1,1,1,1,1,1,1,1,1,1,1,1,1,1,1,1,1,.,.</li>
			<li>.,1,1,1,1,1,1,1,1,1,1,1,1,1,1,1,1,1,.,.</li>
			<li>.,1,1,1,1,1,1,1,1,1,1,1,1,1,1,1,1,1,.,.</li>
			<li>.,1,1,1,1,1,1,1,1,1,1,1,1,1,1,1,1,1,.,.</li>
			<li>.,1,1,1,1,1,1,1,1,1,1,1,1,1,1,1,1,1,.,.</li>
			<li>.,1,1,1,1,1,1,1,1,1,1,1,1,1,1,1,1,1,.,.</li>
			<li>.,1,1,1,1,1,1,1,1,1,1,1,1,1,1,1,1,1,.,.</li>
			<li>.,1,1,1,1,1,1,1,1,1,1,1,1,1,1,1,1,1,.,.</li>
			<li>.,1,1,1,1,1,1,1,1,1,1,1,1,1,1,1,1,1,.,.</li>
			<li>.,1,1,1,1,1,1,1,1,1,1,1,1,1,1,1,1,.,.,.</li>
			<li>.,.,.,.,1,1,1,1,1,1,1,1,1,1,1,1,1,.,.,.</li>
			<li>.,.,.,.,1,1,1,1,1,1,1,1,1,1,1,1,1,.,.,.</li>
			<li>.,.,.,.,1,1,1,1,1,1,1,1,1,1,1,1,1,.,.,.</li>
			<li>.,.,.,.,1,1,1,1,1,1,1,1,1,1,1,1,1,.,.,.</li>
			<li>.,.,.,.,1,1,1,1,1,1,1,1,1,1,1,1,1,.,.,.</li>
			<li>.,.,.,.,1,1,1,1,1,1,1,1,1,1,1,1,1,.,.,.</li>
			<li>.,.,.,.,1,1,1,1,1,1,1,1,1,1,1,1,1,.,.,.</li>
			<li>.,.,.,.,.,.,.,.,1,1,1,1,1,.,.,.,.,.,.,.</li>
			<li>.,.,.,.,.,.,.,.,.,.,.,.,.,.,.,.,.,.,.,.</li>
		</roofGrid>
		<terrainGrid>
			<li>PavedTile,PavedTile,PavedTile,PavedTile,PavedTile,PavedTile,PavedTile,PavedTile,PavedTile,PavedTile,PavedTile,PavedTile,PavedTile,PavedTile,PavedTile,PavedTile,PavedTile,PavedTile,PavedTile,PavedTile</li>
			<li>PavedTile,PavedTile,PavedTile,PavedTile,PavedTile,PavedTile,PavedTile,PavedTile,PavedTile,PavedTile,PavedTile,PavedTile,PavedTile,PavedTile,PavedTile,PavedTile,PavedTile,PavedTile,PavedTile,PavedTile</li>
			<li>PavedTile,PavedTile,PavedTile,PavedTile,PavedTile,PavedTile,VFE_FactoryPath,VFE_FactoryPath,VFE_FactoryPath,VFE_FactoryPath,VFE_FactoryPath,VFE_FactoryPath,VFE_FactoryPath,VFE_FactoryPath,VFE_FactoryPath,PavedTile,PavedTile,PavedTile,PavedTile,PavedTile</li>
			<li>PavedTile,PavedTile,PavedTile,PavedTile,PavedTile,PavedTile,VFE_FactoryPath,VFE_FactoryFloor,VFE_FactoryFloor,VFE_FactoryFloor,VFE_FactoryFloor,VFE_FactoryFloor,VFE_FactoryFloor,VFE_FactoryFloor,VFE_FactoryPath,PavedTile,PavedTile,PavedTile,PavedTile,PavedTile</li>
			<li>PavedTile,PavedTile,PavedTile,PavedTile,PavedTile,PavedTile,VFE_FactoryPath,VFE_FactoryFloor,VFE_FactoryFloor,VFE_FactoryFloor,VFE_FactoryFloor,VFE_FactoryFloor,VFE_FactoryFloor,VFE_FactoryFloor,VFE_FactoryPath,PavedTile,PavedTile,PavedTile,PavedTile,PavedTile</li>
			<li>PavedTile,PavedTile,PavedTile,PavedTile,PavedTile,PavedTile,VFE_FactoryPath,VFE_FactoryFloor,VFE_FactoryFloor,VFE_FactoryFloor,VFE_FactoryFloor,VFE_FactoryFloor,VFE_FactoryFloor,VFE_FactoryFloor,VFE_FactoryPath,PavedTile,PavedTile,PavedTile,PavedTile,.</li>
			<li>PavedTile,PavedTile,PavedTile,PavedTile,PavedTile,PavedTile,VFE_FactoryFloor,VFE_FactoryFloor,VFE_FactoryFloor,VFE_FactoryFloor,VFE_FactoryFloor,VFE_FactoryFloor,VFE_FactoryFloor,VFE_FactoryFloor,VFE_FactoryFloor,PavedTile,PavedTile,PavedTile,PavedTile,.</li>
			<li>PavedTile,PavedTile,PavedTile,PavedTile,PavedTile,PavedTile,VFE_FactoryPath,VFE_FactoryFloor,VFE_FactoryFloor,VFE_FactoryFloor,VFE_FactoryFloor,VFE_FactoryFloor,VFE_FactoryFloor,VFE_FactoryFloor,VFE_FactoryPath,PavedTile,PavedTile,PavedTile,PavedTile,.</li>
			<li>PavedTile,PavedTile,PavedTile,PavedTile,PavedTile,PavedTile,VFE_FactoryPath,VFE_FactoryFloor,VFE_FactoryFloor,VFE_FactoryFloor,VFE_FactoryFloor,VFE_FactoryFloor,VFE_FactoryFloor,VFE_FactoryFloor,VFE_FactoryPath,PavedTile,PavedTile,PavedTile,PavedTile,.</li>
			<li>PavedTile,PavedTile,PavedTile,PavedTile,PavedTile,PavedTile,VFE_FactoryPath,VFE_FactoryFloor,VFE_FactoryFloor,VFE_FactoryFloor,VFE_FactoryFloor,VFE_FactoryFloor,VFE_FactoryFloor,VFE_FactoryFloor,VFE_FactoryPath,PavedTile,PavedTile,PavedTile,PavedTile,.</li>
			<li>PavedTile,PavedTile,PavedTile,PavedTile,PavedTile,PavedTile,VFE_FactoryPath,VFE_FactoryFloor,VFE_FactoryFloor,VFE_FactoryFloor,VFE_FactoryFloor,VFE_FactoryFloor,VFE_FactoryFloor,VFE_FactoryFloor,VFE_FactoryPath,PavedTile,PavedTile,PavedTile,PavedTile,.</li>
			<li>PavedTile,PavedTile,PavedTile,PavedTile,PavedTile,PavedTile,VFE_FactoryPath,VFE_FactoryFloor,VFE_FactoryFloor,VFE_FactoryFloor,VFE_FactoryFloor,VFE_FactoryFloor,VFE_FactoryFloor,VFE_FactoryFloor,VFE_FactoryPath,PavedTile,PavedTile,PavedTile,PavedTile,.</li>
			<li>PavedTile,PavedTile,PavedTile,PavedTile,PavedTile,PavedTile,VFE_FactoryPath,VFE_FactoryFloor,VFE_FactoryFloor,VFE_FactoryFloor,VFE_FactoryFloor,VFE_FactoryFloor,VFE_FactoryFloor,VFE_FactoryFloor,VFE_FactoryPath,PavedTile,PavedTile,PavedTile,PavedTile,.</li>
			<li>PavedTile,PavedTile,PavedTile,PavedTile,PavedTile,PavedTile,VFE_FactoryFloor,VFE_FactoryFloor,VFE_FactoryFloor,VFE_FactoryFloor,VFE_FactoryFloor,VFE_FactoryFloor,VFE_FactoryFloor,VFE_FactoryFloor,VFE_FactoryFloor,PavedTile,PavedTile,PavedTile,PavedTile,PavedTile</li>
			<li>PavedTile,PavedTile,PavedTile,PavedTile,PavedTile,PavedTile,VFE_FactoryPath,VFE_FactoryFloor,VFE_FactoryFloor,VFE_FactoryFloor,VFE_FactoryFloor,VFE_FactoryFloor,VFE_FactoryFloor,VFE_FactoryFloor,VFE_FactoryPath,PavedTile,PavedTile,PavedTile,PavedTile,PavedTile</li>
			<li>PavedTile,PavedTile,PavedTile,PavedTile,PavedTile,PavedTile,VFE_FactoryPath,VFE_FactoryFloor,VFE_FactoryFloor,VFE_FactoryFloor,VFE_FactoryFloor,VFE_FactoryFloor,VFE_FactoryFloor,VFE_FactoryFloor,VFE_FactoryPath,PavedTile,PavedTile,PavedTile,PavedTile,PavedTile</li>
			<li>PavedTile,PavedTile,PavedTile,PavedTile,PavedTile,PavedTile,VFE_FactoryPath,VFE_FactoryFloor,VFE_FactoryFloor,VFE_FactoryFloor,VFE_FactoryFloor,VFE_FactoryFloor,VFE_FactoryFloor,VFE_FactoryFloor,VFE_FactoryPath,PavedTile,PavedTile,PavedTile,PavedTile,PavedTile</li>
			<li>PavedTile,PavedTile,PavedTile,PavedTile,PavedTile,PavedTile,VFE_FactoryPath,VFE_FactoryFloor,VFE_FactoryFloor,VFE_FactoryFloor,VFE_FactoryFloor,VFE_FactoryFloor,VFE_FactoryFloor,VFE_FactoryFloor,VFE_FactoryPath,PavedTile,PavedTile,PavedTile,PavedTile,PavedTile</li>
			<li>PavedTile,PavedTile,PavedTile,PavedTile,PavedTile,PavedTile,VFE_FactoryPath,VFE_FactoryFloor,VFE_FactoryFloor,VFE_FactoryFloor,VFE_FactoryFloor,VFE_FactoryFloor,VFE_FactoryFloor,VFE_FactoryFloor,VFE_FactoryPath,PavedTile,PavedTile,PavedTile,PavedTile,PavedTile</li>
			<li>PavedTile,PavedTile,PavedTile,PavedTile,PavedTile,PavedTile,VFE_FactoryPath,VFE_FactoryPath,VFE_FactoryPath,VFE_FactoryFloor,VFE_FactoryFloor,VFE_FactoryFloor,VFE_FactoryPath,VFE_FactoryPath,VFE_FactoryPath,PavedTile,PavedTile,PavedTile,PavedTile,PavedTile</li>
			<li>.,.,.,PavedTile,PavedTile,PavedTile,VFE_FactoryPath,VFE_FactoryPath,VFE_FactoryPath,VFE_FactoryPath,VFE_FactoryPath,VFE_FactoryPath,VFE_FactoryPath,VFE_FactoryPath,VFE_FactoryPath,PavedTile,PavedTile,PavedTile,.,.</li>
			<li>.,.,.,PavedTile,PavedTile,PavedTile,PavedTile,PavedTile,PavedTile,PavedTile,PavedTile,PavedTile,PavedTile,PavedTile,PavedTile,PavedTile,PavedTile,PavedTile,.,.</li>
			<li>.,.,.,PavedTile,PavedTile,PavedTile,PavedTile,PavedTile,PavedTile,PavedTile,PavedTile,PavedTile,PavedTile,PavedTile,PavedTile,PavedTile,PavedTile,PavedTile,.,.</li>
			<li>.,.,.,PavedTile,PavedTile,PavedTile,PavedTile,PavedTile,PavedTile,PavedTile,PavedTile,PavedTile,PavedTile,PavedTile,PavedTile,PavedTile,PavedTile,PavedTile,.,.</li>
			<li>.,.,.,.,.,.,.,PavedTile,PavedTile,PavedTile,PavedTile,PavedTile,PavedTile,PavedTile,.,.,.,.,.,.</li>
		</terrainGrid>
		<modRequirements>
			<li>oskarpotocki.vfe.mechanoid</li>
		</modRequirements>
	</KCSG.StructureLayoutDef>
	<KCSG.StructureLayoutDef>
		<defName>AP_Prefab_Production_Factory_3</defName>
		<spawnConduits>false</spawnConduits>
		<layouts>
			<li>
				<li>.,.,.,Fence_Steel,.,StandingLamp,.,.,Fence_Steel,.,.,.,.,.</li>
				<li>.,Wall_Steel,Wall_Steel,Wall_Steel,Wall_Steel,Wall_Steel,Autodoor_Steel,Wall_Steel,Wall_Steel,Wall_Steel,Wall_Steel,.,.,.</li>
				<li>Wall_Steel,Wall_Steel,.,.,.,PowerConduit,.,.,.,.,Wall_Steel,Wall_Steel,.,.</li>
				<li>Wall_Steel,.,.,.,.,PowerConduit,.,.,.,.,Shelf_Steel_West,Wall_Steel,.,.</li>
				<li>Wall_Steel,Shelf_Steel_East,.,.,VFEM_MasonryAndMetallicsFactory_AutomaticDrill_South,PowerConduit,.,VFEM_MasonryAndMetallicsFactory_AutomaticDrill_South,.,.,.,Wall_Steel,.,.</li>
				<li>Wall_Steel,.,.,.,.,PowerConduit,.,.,.,.,Shelf_Steel_West,Wall_Steel,.,.</li>
				<li>Wall_Steel,Shelf_Steel_East,.,.,VFEM_HeavyHopper_North,PowerConduit,.,VFEM_HeavyHopper_North,.,.,.,Wall_Steel,.,.</li>
				<li>Wall_Steel,Wall_Steel,.,.,.,PowerConduit,.,.,.,.,StandingLamp,Wall_Steel,Wall_Steel,Fence_Steel</li>
				<li>.,Wall_Steel,.,.,.,PowerConduit,.,.,.,.,.,.,Autodoor_Steel,.</li>
				<li>.,Wall_Steel,.,.,VFEM_MasonryAndMetallicsFactory_MasonrySaw_North,PowerConduit,.,VFEM_MasonryAndMetallicsFactory_MasonrySaw_North,.,.,Battery_East,.,Wall_Steel,.</li>
				<li>.,Wall_Steel,.,.,.,PowerConduit,.,.,.,.,Battery_North,Wall_Steel,Wall_Steel,.</li>
				<li>.,Wall_Steel,PowerConduit,PowerConduit,PowerConduit,PowerConduit,PowerConduit,PowerConduit,PowerConduit,PowerConduit,.,Wall_Steel,StandingLamp,.</li>
				<li>.,Wall_Steel,.,.,VFEM_HeavyHopper_South,.,.,VFEM_HeavyHopper_South,.,.,Wall_Steel,Wall_Steel,Fence_Steel,Fence_Steel</li>
				<li>.,Wall_Steel,StandingLamp,.,.,.,.,.,.,.,Wall_Steel,.,.,.</li>
				<li>.,Wall_Steel,.,.,.,.,.,.,.,TableStonecutter_WoodLog_East,Wall_Steel,.,.,.</li>
				<li>.,Wall_Steel,Shelf_Steel_East,.,.,TableStonecutter_WoodLog_North,.,ToolCabinet_North,.,.,Wall_Steel,.,.,.</li>
				<li>.,Wall_Steel,Wall_Steel,.,ShelfSmall_Steel_West,Wall_Steel,Wall_Steel,Wall_Steel,Wall_Steel,Wall_Steel,Wall_Steel,.,.,.</li>
				<li>.,.,Wall_Steel,Autodoor_Steel,Wall_Steel,Wall_Steel,StandingLamp,.,.,.,.,.,.,.</li>
			</li>
			<li>
				<li>.,.,.,.,.,.,.,.,.,.,.,.,.,.</li>
				<li>.,PowerConduit,PowerConduit,PowerConduit,PowerConduit,PowerConduit,PowerConduit,PowerConduit,PowerConduit,PowerConduit,PowerConduit,.,.,.</li>
				<li>PowerConduit,PowerConduit,.,.,.,.,.,.,.,.,PowerConduit,PowerConduit,.,.</li>
				<li>PowerConduit,.,.,.,.,.,.,.,.,.,.,PowerConduit,.,.</li>
				<li>PowerConduit,.,.,.,.,.,.,.,.,.,.,PowerConduit,.,.</li>
				<li>PowerConduit,.,.,.,.,.,.,.,.,.,.,PowerConduit,.,.</li>
				<li>PowerConduit,.,.,.,.,VFE_MechanoidConstructionLamp,.,.,.,.,.,PowerConduit,.,.</li>
				<li>PowerConduit,PowerConduit,.,.,.,.,.,.,.,.,.,PowerConduit,PowerConduit,.</li>
				<li>.,PowerConduit,.,.,.,.,.,.,.,.,.,.,PowerConduit,.</li>
				<li>.,PowerConduit,.,.,.,.,.,.,.,.,.,.,PowerConduit,.</li>
				<li>.,PowerConduit,.,.,.,.,.,.,.,.,.,PowerConduit,PowerConduit,.</li>
				<li>.,PowerConduit,.,.,.,.,.,.,.,.,.,PowerConduit,.,.</li>
				<li>.,PowerConduit,.,.,.,.,.,.,.,.,PowerConduit,PowerConduit,.,.</li>
				<li>.,PowerConduit,.,.,.,.,.,.,.,.,PowerConduit,.,.,.</li>
				<li>.,PowerConduit,.,.,.,.,.,.,.,.,PowerConduit,.,.,.</li>
				<li>.,PowerConduit,.,.,.,.,.,.,.,.,PowerConduit,.,.,.</li>
				<li>.,PowerConduit,PowerConduit,.,.,PowerConduit,PowerConduit,PowerConduit,PowerConduit,PowerConduit,PowerConduit,.,.,.</li>
				<li>.,.,PowerConduit,PowerConduit,PowerConduit,PowerConduit,.,.,.,.,.,.,.,.</li>
			</li>
		</layouts>
		<roofGrid>
			<li>.,.,.,.,.,.,.,.,.,.,.,.,.,.</li>
			<li>.,1,1,1,1,1,1,1,1,1,1,.,.,.</li>
			<li>1,1,1,1,1,1,1,1,1,1,1,1,.,.</li>
			<li>1,1,1,1,1,1,1,1,1,1,1,1,.,.</li>
			<li>1,1,1,1,1,1,1,1,1,1,1,1,.,.</li>
			<li>1,1,1,1,1,1,1,1,1,1,1,1,.,.</li>
			<li>1,1,1,1,1,1,1,1,1,1,1,1,.,.</li>
			<li>1,1,1,1,1,1,1,1,1,1,1,1,1,.</li>
			<li>.,1,1,1,1,1,1,1,1,1,1,1,1,.</li>
			<li>.,1,1,1,1,1,1,1,1,1,1,1,1,.</li>
			<li>.,1,1,1,1,1,1,1,1,1,1,1,1,.</li>
			<li>.,1,1,1,1,1,1,1,1,1,1,1,.,.</li>
			<li>.,1,1,1,1,1,1,1,1,1,1,1,.,.</li>
			<li>.,1,1,1,1,1,1,1,1,1,1,.,.,.</li>
			<li>.,1,1,1,1,1,1,1,1,1,1,.,.,.</li>
			<li>.,1,1,1,1,1,1,1,1,1,1,.,.,.</li>
			<li>.,1,1,1,1,1,1,1,1,1,1,.,.,.</li>
			<li>.,.,1,1,1,1,.,.,.,.,.,.,.,.</li>
		</roofGrid>
		<terrainGrid>
			<li>PavedTile,PavedTile,PavedTile,PavedTile,PavedTile,PavedTile,PavedTile,PavedTile,PavedTile,PavedTile,PavedTile,PavedTile,.,.</li>
			<li>PavedTile,PavedTile,VFE_FactoryFloor,VFE_FactoryFloor,MetalTile,MetalTile,MetalTile,MetalTile,VFE_FactoryFloor,VFE_FactoryFloor,VFE_FactoryFloor,PavedTile,PavedTile,.</li>
			<li>VFE_FactoryFloor,VFE_FactoryFloor,VFE_FactoryPath,VFE_FactoryPath,VFE_FactoryPath,VFE_FactoryPath,VFE_FactoryPath,VFE_FactoryPath,VFE_FactoryPath,VFE_FactoryPath,VFE_FactoryFloor,VFE_FactoryFloor,PavedTile,.</li>
			<li>VFE_FactoryFloor,MetalTile,VFE_FactoryPath,VFE_FactoryFloor,VFE_FactoryFloor,VFE_FactoryFloor,VFE_FactoryFloor,VFE_FactoryFloor,VFE_FactoryFloor,VFE_FactoryPath,MetalTile,VFE_FactoryFloor,PavedTile,.</li>
			<li>VFE_FactoryFloor,MetalTile,VFE_FactoryPath,VFE_FactoryFloor,VFE_FactoryFloor,VFE_FactoryFloor,VFE_FactoryFloor,VFE_FactoryFloor,VFE_FactoryFloor,VFE_FactoryPath,MetalTile,VFE_FactoryFloor,PavedTile,.</li>
			<li>VFE_FactoryFloor,MetalTile,VFE_FactoryPath,VFE_FactoryFloor,VFE_FactoryFloor,VFE_FactoryFloor,VFE_FactoryFloor,VFE_FactoryFloor,VFE_FactoryFloor,VFE_FactoryPath,MetalTile,VFE_FactoryFloor,PavedTile,.</li>
			<li>VFE_FactoryFloor,MetalTile,VFE_FactoryPath,VFE_FactoryFloor,VFE_FactoryFloor,VFE_FactoryFloor,VFE_FactoryFloor,VFE_FactoryFloor,VFE_FactoryFloor,VFE_FactoryPath,MetalTile,VFE_FactoryFloor,PavedTile,PavedTile</li>
			<li>VFE_FactoryFloor,VFE_FactoryFloor,VFE_FactoryPath,VFE_FactoryFloor,VFE_FactoryFloor,VFE_FactoryFloor,VFE_FactoryFloor,VFE_FactoryFloor,VFE_FactoryFloor,VFE_FactoryPath,MetalTile,VFE_FactoryFloor,VFE_FactoryFloor,PavedTile</li>
			<li>PavedTile,VFE_FactoryFloor,VFE_FactoryPath,VFE_FactoryFloor,VFE_FactoryFloor,VFE_FactoryFloor,VFE_FactoryFloor,VFE_FactoryFloor,VFE_FactoryFloor,VFE_FactoryPath,MetalTile,MetalTile,MetalTile,PavedTile</li>
			<li>PavedTile,VFE_FactoryFloor,VFE_FactoryPath,VFE_FactoryFloor,VFE_FactoryFloor,VFE_FactoryFloor,VFE_FactoryFloor,VFE_FactoryFloor,VFE_FactoryFloor,VFE_FactoryPath,MetalTile,MetalTile,VFE_FactoryFloor,PavedTile</li>
			<li>PavedTile,VFE_FactoryFloor,VFE_FactoryPath,VFE_FactoryFloor,VFE_FactoryFloor,VFE_FactoryFloor,VFE_FactoryFloor,VFE_FactoryFloor,VFE_FactoryFloor,VFE_FactoryPath,MetalTile,VFE_FactoryFloor,VFE_FactoryFloor,PavedTile</li>
			<li>PavedTile,VFE_FactoryFloor,VFE_FactoryPath,VFE_FactoryFloor,VFE_FactoryFloor,VFE_FactoryFloor,VFE_FactoryFloor,VFE_FactoryFloor,VFE_FactoryFloor,VFE_FactoryPath,MetalTile,VFE_FactoryFloor,PavedTile,PavedTile</li>
			<li>PavedTile,VFE_FactoryFloor,VFE_FactoryPath,VFE_FactoryFloor,VFE_FactoryFloor,VFE_FactoryFloor,VFE_FactoryFloor,VFE_FactoryFloor,VFE_FactoryFloor,VFE_FactoryPath,VFE_FactoryFloor,VFE_FactoryFloor,PavedTile,PavedTile</li>
			<li>PavedTile,VFE_FactoryFloor,VFE_FactoryPath,VFE_FactoryPath,VFE_FactoryPath,VFE_FactoryPath,VFE_FactoryPath,VFE_FactoryPath,VFE_FactoryPath,VFE_FactoryPath,VFE_FactoryFloor,PavedTile,PavedTile,PavedTile</li>
			<li>PavedTile,VFE_FactoryFloor,PavedTile,PavedTile,PavedTile,PavedTile,PavedTile,PavedTile,PavedTile,PavedTile,VFE_FactoryFloor,PavedTile,.,.</li>
			<li>PavedTile,VFE_FactoryFloor,PavedTile,PavedTile,PavedTile,PavedTile,PavedTile,PavedTile,PavedTile,PavedTile,VFE_FactoryFloor,PavedTile,.,.</li>
			<li>PavedTile,VFE_FactoryFloor,VFE_FactoryFloor,PavedTile,PavedTile,VFE_FactoryFloor,VFE_FactoryFloor,VFE_FactoryFloor,VFE_FactoryFloor,VFE_FactoryFloor,VFE_FactoryFloor,PavedTile,.,.</li>
			<li>PavedTile,PavedTile,VFE_FactoryFloor,PavedTile,VFE_FactoryFloor,VFE_FactoryFloor,PavedTile,PavedTile,PavedTile,PavedTile,PavedTile,PavedTile,.,.</li>
		</terrainGrid>
		<modRequirements>
			<li>oskarpotocki.vfe.mechanoid</li>
		</modRequirements>
	</KCSG.StructureLayoutDef>
	<KCSG.StructureLayoutDef>
		<defName>AP_Prefab_Production_Factory_4</defName>
		<spawnConduits>false</spawnConduits>
		<layouts>
			<li>
				<li>.,.,.,.,.,.,.,.,.,.,.,.,.,.,.,.,.,.,.,.,.,.,.,.,.</li>
				<li>.,Wall_Steel,Wall_Steel,Wall_Steel,Wall_Steel,Wall_Steel,Wall_Steel,Wall_Steel,Wall_Steel,Wall_Steel,Wall_Steel,Wall_Steel,Wall_Steel,Wall_Steel,Wall_Steel,Wall_Steel,Wall_Steel,Wall_Steel,Wall_Steel,Wall_Steel,Wall_Steel,Wall_Steel,Wall_Steel,Wall_Steel,.</li>
				<li>.,Wall_Steel,Battery_North,.,.,.,.,.,.,.,.,.,PowerConduit,.,.,.,.,.,.,.,.,.,Battery_North,Wall_Steel,.</li>
				<li>.,Wall_Steel,.,.,VFEM_HeavyHopper_East,.,.,.,.,.,.,.,PowerConduit,.,.,.,.,.,.,.,.,.,.,Wall_Steel,.</li>
				<li>Fence_Steel,Wall_Steel,Wall_Steel,.,VFEM_HeavyHopper_East,.,.,.,VFEM_ProvisionsPackagingFactory_MeatGrinder_East,.,.,.,VFEM_HeavyHopper_East,.,.,.,VFEM_MedicinalCompoundingFactory_NeutroamineInfuser_East,.,.,.,VFEM_HeavyHopper_West,.,Wall_Steel,Wall_Steel,Fence_Steel</li>
				<li>Fence_Steel,StandingLamp,Wall_Steel,PowerConduit,VFEM_HeavyHopper_East,PowerConduit,PowerConduit,PowerConduit,PowerConduit,PowerConduit,PowerConduit,PowerConduit,PowerConduit,PowerConduit,PowerConduit,PowerConduit,PowerConduit,PowerConduit,PowerConduit,PowerConduit,PowerConduit,PowerConduit,Wall_Steel,StandingLamp,Fence_Steel</li>
				<li>.,.,PowerConduit,.,VFEM_HeavyHopper_East,.,.,.,.,.,.,.,PowerConduit,.,.,.,.,.,.,.,.,.,PowerConduit,.,.</li>
				<li>Fence_Steel,.,Wall_Steel,.,VFEM_HeavyHopper_East,.,.,.,VFEM_ProvisionsPackagingFactory_MeatGrinder_East,.,.,.,VFEM_HeavyHopper_East,.,.,.,VFEM_MedicinalCompoundingFactory_NeutroamineInfuser_East,.,.,.,VFEM_HeavyHopper_West,.,Wall_Steel,.,Fence_Steel</li>
				<li>Fence_Steel,Wall_Steel,Wall_Steel,.,VFEM_HeavyHopper_East,.,.,.,.,.,.,.,PowerConduit,.,.,.,.,.,.,.,.,.,Wall_Steel,Wall_Steel,Fence_Steel</li>
				<li>.,Wall_Steel,ToolCabinet_West,.,.,.,.,.,.,.,.,.,PowerConduit,.,.,.,.,.,.,.,.,.,.,Wall_Steel,.</li>
				<li>.,Wall_Steel,.,.,.,.,.,.,.,.,.,.,PowerConduit,.,.,.,.,.,.,.,.,.,ToolCabinet_East,Wall_Steel,.</li>
				<li>.,Wall_Steel,.,Shelf_Steel_South,.,.,StandingLamp,.,Shelf_Steel_South,Wall_Steel,Wall_Steel,Wall_Steel,Autodoor_Steel,Wall_Steel,Wall_Steel,Wall_Steel,.,Shelf_Steel_South,StandingLamp,.,.,.,Shelf_Steel_South,Wall_Steel,.</li>
				<li>.,Wall_Steel,Wall_Steel,Wall_Steel,.,DrugLab_Steel_North,.,Wall_Steel,Wall_Steel,Wall_Steel,.,StandingLamp,.,.,.,Wall_Steel,Wall_Steel,Wall_Steel,.,DrugLab_Steel_North,.,Wall_Steel,Wall_Steel,Wall_Steel,.</li>
				<li>.,.,.,Wall_Steel,Wall_Steel,Wall_Steel,Wall_Steel,Wall_Steel,.,.,.,.,.,.,.,.,.,Wall_Steel,Wall_Steel,Wall_Steel,Wall_Steel,Wall_Steel,.,.,.</li>
				<li>.,.,.,.,.,.,.,Fence_Steel,Fence_Steel,Fence_Steel,Fence_Steel,.,.,.,Fence_Steel,Fence_Steel,Fence_Steel,Fence_Steel,.,.,.,.,.,.,.</li>
			</li>
			<li>
				<li>.,.,.,.,.,.,.,.,.,.,.,.,.,.,.,.,.,.,.,.,.,.,.,.,.</li>
				<li>.,PowerConduit,PowerConduit,PowerConduit,PowerConduit,PowerConduit,PowerConduit,PowerConduit,PowerConduit,PowerConduit,PowerConduit,PowerConduit,PowerConduit,PowerConduit,PowerConduit,PowerConduit,PowerConduit,PowerConduit,PowerConduit,PowerConduit,PowerConduit,PowerConduit,PowerConduit,PowerConduit,.</li>
				<li>.,PowerConduit,.,.,.,.,.,.,.,.,.,.,.,.,.,.,.,.,.,.,.,.,.,PowerConduit,.</li>
				<li>.,PowerConduit,.,.,.,.,.,.,.,.,.,.,StandingLamp,.,.,.,.,.,.,.,.,.,.,PowerConduit,.</li>
				<li>.,PowerConduit,PowerConduit,.,.,.,.,.,.,.,.,.,PowerConduit,.,.,.,.,.,.,.,.,.,PowerConduit,PowerConduit,.</li>
				<li>.,.,PowerConduit,.,PowerConduit,.,.,.,.,.,.,.,.,.,.,.,.,.,.,.,.,.,PowerConduit,.,.</li>
				<li>.,.,Autodoor_Steel,.,.,.,.,.,.,.,.,.,VFE_MechanoidConstructionLamp,.,.,.,.,.,.,.,.,.,Autodoor_Steel,.,.</li>
				<li>.,.,PowerConduit,.,.,.,.,.,.,.,.,.,PowerConduit,.,.,.,.,.,.,.,.,.,PowerConduit,.,.</li>
				<li>.,PowerConduit,PowerConduit,.,.,.,.,.,.,.,.,.,.,.,.,.,.,.,.,.,.,.,PowerConduit,PowerConduit,.</li>
				<li>.,PowerConduit,.,.,.,.,.,.,.,.,.,.,.,.,.,.,.,.,.,.,.,.,.,PowerConduit,.</li>
				<li>.,PowerConduit,.,.,.,.,.,.,.,.,.,.,.,.,.,.,.,.,.,.,.,.,.,PowerConduit,.</li>
				<li>.,PowerConduit,.,.,.,.,.,.,.,PowerConduit,PowerConduit,PowerConduit,PowerConduit,PowerConduit,PowerConduit,PowerConduit,.,.,.,.,.,.,.,PowerConduit,.</li>
				<li>.,PowerConduit,PowerConduit,PowerConduit,.,.,.,PowerConduit,PowerConduit,PowerConduit,.,.,.,.,.,PowerConduit,PowerConduit,PowerConduit,.,.,.,PowerConduit,PowerConduit,PowerConduit,.</li>
				<li>.,.,.,PowerConduit,PowerConduit,PowerConduit,PowerConduit,PowerConduit,.,.,.,.,.,.,.,.,.,PowerConduit,PowerConduit,PowerConduit,PowerConduit,PowerConduit,.,.,.</li>
				<li>.,.,.,.,.,.,.,.,.,.,.,.,.,.,.,.,.,.,.,.,.,.,.,.,.</li>
			</li>
		</layouts>
		<roofGrid>
			<li>.,.,.,.,.,.,.,.,.,.,.,.,.,.,.,.,.,.,.,.,.,.,.,.,.</li>
			<li>.,1,1,1,1,1,1,1,1,1,1,1,1,1,1,1,1,1,1,1,1,1,1,1,.</li>
			<li>.,1,1,1,1,1,1,1,1,1,1,1,1,1,1,1,1,1,1,1,1,1,1,1,.</li>
			<li>.,1,1,1,1,1,1,1,1,1,1,1,1,1,1,1,1,1,1,1,1,1,1,1,.</li>
			<li>.,1,1,1,1,1,1,1,1,1,1,1,1,1,1,1,1,1,1,1,1,1,1,1,.</li>
			<li>.,.,1,1,1,1,1,1,1,1,1,1,1,1,1,1,1,1,1,1,1,1,1,.,.</li>
			<li>.,.,1,1,1,1,1,1,1,1,1,1,1,1,1,1,1,1,1,1,1,1,1,.,.</li>
			<li>.,.,1,1,1,1,1,1,1,1,1,1,1,1,1,1,1,1,1,1,1,1,1,.,.</li>
			<li>.,1,1,1,1,1,1,1,1,1,1,1,1,1,1,1,1,1,1,1,1,1,1,1,.</li>
			<li>.,1,1,1,1,1,1,1,1,1,1,1,1,1,1,1,1,1,1,1,1,1,.,1,.</li>
			<li>.,1,1,1,1,1,1,1,1,1,1,1,1,1,1,1,1,1,1,1,1,1,.,1,.</li>
			<li>.,1,1,1,1,1,1,1,1,1,1,1,1,1,1,1,1,1,1,1,1,1,1,1,.</li>
			<li>.,1,1,1,1,1,1,1,1,1,.,.,.,.,.,1,1,1,1,1,1,1,1,1,.</li>
			<li>.,.,.,1,1,1,1,1,.,.,.,.,.,.,.,.,.,1,1,1,1,1,.,.,.</li>
			<li>.,.,.,.,.,.,.,.,.,.,.,.,.,.,.,.,.,.,.,.,.,.,.,.,.</li>
		</roofGrid>
		<terrainGrid>
			<li>PavedTile,PavedTile,PavedTile,PavedTile,PavedTile,PavedTile,PavedTile,PavedTile,PavedTile,PavedTile,PavedTile,PavedTile,PavedTile,PavedTile,PavedTile,PavedTile,PavedTile,PavedTile,PavedTile,PavedTile,PavedTile,PavedTile,PavedTile,PavedTile,PavedTile</li>
			<li>PavedTile,VFE_FactoryFloor,VFE_FactoryFloor,VFE_FactoryFloor,VFE_FactoryFloor,VFE_FactoryFloor,VFE_FactoryFloor,VFE_FactoryFloor,VFE_FactoryFloor,VFE_FactoryFloor,VFE_FactoryFloor,VFE_FactoryFloor,VFE_FactoryFloor,VFE_FactoryFloor,VFE_FactoryFloor,VFE_FactoryFloor,VFE_FactoryFloor,VFE_FactoryFloor,VFE_FactoryFloor,VFE_FactoryFloor,VFE_FactoryFloor,VFE_FactoryFloor,VFE_FactoryFloor,VFE_FactoryFloor,PavedTile</li>
			<li>PavedTile,VFE_FactoryFloor,PavedTile,VFE_FactoryPath,VFE_FactoryPath,VFE_FactoryPath,VFE_FactoryPath,VFE_FactoryPath,VFE_FactoryPath,VFE_FactoryPath,VFE_FactoryPath,VFE_FactoryPath,VFE_FactoryPath,VFE_FactoryPath,VFE_FactoryPath,VFE_FactoryPath,VFE_FactoryPath,VFE_FactoryPath,VFE_FactoryPath,VFE_FactoryPath,VFE_FactoryPath,VFE_FactoryPath,PavedTile,VFE_FactoryFloor,PavedTile</li>
			<li>PavedTile,VFE_FactoryFloor,PavedTile,VFE_FactoryPath,VFE_FactoryFloor,VFE_FactoryFloor,VFE_FactoryFloor,VFE_FactoryFloor,VFE_FactoryFloor,VFE_FactoryFloor,VFE_FactoryFloor,VFE_FactoryFloor,VFE_FactoryFloor,VFE_FactoryFloor,VFE_FactoryFloor,VFE_FactoryFloor,VFE_FactoryFloor,VFE_FactoryFloor,VFE_FactoryFloor,VFE_FactoryFloor,VFE_FactoryFloor,VFE_FactoryPath,PavedTile,VFE_FactoryFloor,PavedTile</li>
			<li>PavedTile,VFE_FactoryFloor,VFE_FactoryFloor,VFE_FactoryPath,VFE_FactoryFloor,VFE_FactoryFloor,VFE_FactoryFloor,VFE_FactoryFloor,VFE_FactoryFloor,VFE_FactoryFloor,VFE_FactoryFloor,VFE_FactoryFloor,VFE_FactoryFloor,VFE_FactoryFloor,VFE_FactoryFloor,VFE_FactoryFloor,VFE_FactoryFloor,VFE_FactoryFloor,VFE_FactoryFloor,VFE_FactoryFloor,VFE_FactoryFloor,VFE_FactoryPath,VFE_FactoryFloor,VFE_FactoryFloor,PavedTile</li>
			<li>PavedTile,PavedTile,VFE_FactoryFloor,VFE_FactoryPath,VFE_FactoryFloor,VFE_FactoryFloor,VFE_FactoryFloor,VFE_FactoryFloor,VFE_FactoryFloor,VFE_FactoryFloor,VFE_FactoryFloor,VFE_FactoryFloor,VFE_FactoryFloor,VFE_FactoryFloor,VFE_FactoryFloor,VFE_FactoryFloor,VFE_FactoryFloor,VFE_FactoryFloor,VFE_FactoryFloor,VFE_FactoryFloor,VFE_FactoryFloor,VFE_FactoryPath,VFE_FactoryFloor,PavedTile,PavedTile</li>
			<li>PavedTile,PavedTile,MetalTile,VFE_FactoryPath,VFE_FactoryFloor,VFE_FactoryFloor,VFE_FactoryFloor,VFE_FactoryFloor,VFE_FactoryFloor,VFE_FactoryFloor,VFE_FactoryFloor,VFE_FactoryFloor,VFE_FactoryFloor,VFE_FactoryFloor,VFE_FactoryFloor,VFE_FactoryFloor,VFE_FactoryFloor,VFE_FactoryFloor,VFE_FactoryFloor,VFE_FactoryFloor,VFE_FactoryFloor,VFE_FactoryPath,MetalTile,PavedTile,PavedTile</li>
			<li>PavedTile,PavedTile,VFE_FactoryFloor,VFE_FactoryPath,VFE_FactoryFloor,VFE_FactoryFloor,VFE_FactoryFloor,VFE_FactoryFloor,VFE_FactoryFloor,VFE_FactoryFloor,VFE_FactoryFloor,VFE_FactoryFloor,VFE_FactoryFloor,VFE_FactoryFloor,VFE_FactoryFloor,VFE_FactoryFloor,VFE_FactoryFloor,VFE_FactoryFloor,VFE_FactoryFloor,VFE_FactoryFloor,VFE_FactoryFloor,VFE_FactoryPath,VFE_FactoryFloor,PavedTile,PavedTile</li>
			<li>PavedTile,VFE_FactoryFloor,VFE_FactoryFloor,VFE_FactoryPath,VFE_FactoryFloor,VFE_FactoryFloor,VFE_FactoryFloor,VFE_FactoryFloor,VFE_FactoryFloor,VFE_FactoryFloor,VFE_FactoryFloor,VFE_FactoryFloor,VFE_FactoryFloor,VFE_FactoryFloor,VFE_FactoryFloor,VFE_FactoryFloor,VFE_FactoryFloor,VFE_FactoryFloor,VFE_FactoryFloor,VFE_FactoryFloor,VFE_FactoryFloor,VFE_FactoryPath,VFE_FactoryFloor,VFE_FactoryFloor,PavedTile</li>
			<li>PavedTile,VFE_FactoryFloor,MetalTile,VFE_FactoryPath,VFE_FactoryPath,VFE_FactoryPath,VFE_FactoryPath,VFE_FactoryPath,VFE_FactoryPath,VFE_FactoryPath,VFE_FactoryPath,VFE_FactoryPath,VFE_FactoryPath,VFE_FactoryPath,VFE_FactoryPath,VFE_FactoryPath,VFE_FactoryPath,VFE_FactoryPath,VFE_FactoryPath,VFE_FactoryPath,VFE_FactoryPath,VFE_FactoryPath,MetalTile,VFE_FactoryFloor,PavedTile</li>
			<li>PavedTile,VFE_FactoryFloor,MetalTile,SterileTile,SterileTile,SterileTile,SterileTile,SterileTile,MetalTile,MetalTile,MetalTile,MetalTile,MetalTile,MetalTile,MetalTile,MetalTile,MetalTile,SterileTile,SterileTile,SterileTile,SterileTile,SterileTile,MetalTile,VFE_FactoryFloor,PavedTile</li>
			<li>PavedTile,VFE_FactoryFloor,MetalTile,MetalTile,SterileTile,SterileTile,SterileTile,MetalTile,MetalTile,VFE_FactoryFloor,VFE_FactoryFloor,VFE_FactoryFloor,MetalTile,VFE_FactoryFloor,VFE_FactoryFloor,VFE_FactoryFloor,MetalTile,MetalTile,SterileTile,SterileTile,SterileTile,MetalTile,MetalTile,VFE_FactoryFloor,PavedTile</li>
			<li>PavedTile,VFE_FactoryFloor,VFE_FactoryFloor,VFE_FactoryFloor,SterileTile,SterileTile,SterileTile,VFE_FactoryFloor,VFE_FactoryFloor,VFE_FactoryFloor,PavedTile,PavedTile,PavedTile,PavedTile,PavedTile,VFE_FactoryFloor,VFE_FactoryFloor,VFE_FactoryFloor,SterileTile,SterileTile,SterileTile,VFE_FactoryFloor,VFE_FactoryFloor,VFE_FactoryFloor,PavedTile</li>
			<li>PavedTile,PavedTile,PavedTile,VFE_FactoryFloor,VFE_FactoryFloor,VFE_FactoryFloor,VFE_FactoryFloor,VFE_FactoryFloor,PavedTile,PavedTile,PavedTile,PavedTile,PavedTile,PavedTile,PavedTile,PavedTile,PavedTile,VFE_FactoryFloor,VFE_FactoryFloor,VFE_FactoryFloor,VFE_FactoryFloor,VFE_FactoryFloor,PavedTile,PavedTile,PavedTile</li>
			<li>.,.,PavedTile,PavedTile,PavedTile,PavedTile,PavedTile,PavedTile,PavedTile,PavedTile,PavedTile,PavedTile,PavedTile,PavedTile,PavedTile,PavedTile,PavedTile,PavedTile,PavedTile,PavedTile,PavedTile,PavedTile,PavedTile,.,.</li>
		</terrainGrid>
		<modRequirements>
			<li>oskarpotocki.vfe.mechanoid</li>
		</modRequirements>
	</KCSG.StructureLayoutDef>
	<KCSG.StructureLayoutDef>
		<defName>AP_Prefab_Production_Mechanitor_1</defName>
		<spawnConduits>false</spawnConduits>
		<layouts>
			<li>
				<li>Fence_Steel,Fence_Steel,.,.,.,.,.,.,.,.,.,StandingLamp,.,.,.,.,.,.,Fence_Steel,Fence_Steel</li>
				<li>Fence_Steel,.,.,Wall_Steel,Wall_Steel,Wall_Steel,Wall_Steel,Wall_Steel,Wall_Steel,.,.,Wall_Steel,Wall_Steel,Wall_Steel,Wall_Steel,Wall_Steel,Wall_Steel,.,.,Fence_Steel</li>
				<li>Fence_Steel,.,.,Wall_Steel,.,.,.,.,Wall_Steel,Autodoor_Steel,Autodoor_Steel,Wall_Steel,.,.,.,.,Wall_Steel,.,.,Fence_Steel</li>
				<li>Fence_Steel,.,StandingLamp,Wall_Steel,.,LargeMechGestator_North,.,.,Wall_Steel,.,.,Wall_Steel,.,LargeMechGestator_North,.,.,Wall_Steel,StandingLamp,.,Fence_Steel</li>
				<li>Fence_Steel,.,Wall_Steel,Wall_Steel,.,.,.,.,Wall_Steel,.,.,Wall_Steel,.,.,.,.,Wall_Steel,Wall_Steel,.,Fence_Steel</li>
				<li>Fence_Steel,.,Wall_Steel,.,.,.,StandingLamp,.,.,.,.,.,.,StandingLamp,.,.,.,Wall_Steel,.,Fence_Steel</li>
				<li>.,.,Wall_Steel,BasicRecharger_East,.,.,.,.,.,.,.,.,.,.,.,.,BasicRecharger_West,Wall_Steel,.,.</li>
				<li>.,Wall_Steel,Wall_Steel,PowerConduit,Battery_North,.,BandNode,.,.,BandNode,.,.,BandNode,.,.,Battery_North,PowerConduit,Wall_Steel,Wall_Steel,.</li>
				<li>.,Wall_Steel,.,.,.,.,.,.,.,.,.,.,.,.,.,.,.,.,Wall_Steel,.</li>
				<li>.,Wall_Steel,.,SubcoreEncoder_West,.,.,.,.,.,.,.,.,.,.,.,.,SubcoreEncoder_East,.,Wall_Steel,.</li>
				<li>.,Wall_Steel,.,.,StandingLamp,.,BandNode,.,.,BandNode,.,.,BandNode,.,.,StandingLamp,.,.,Wall_Steel,.</li>
				<li>.,Wall_Steel,Wall_Steel,.,.,.,.,.,.,.,.,.,.,.,.,.,.,Wall_Steel,Wall_Steel,.</li>
				<li>.,.,Wall_Steel,.,SubcoreSoftscanner_West,.,.,.,.,.,.,.,.,.,.,SubcoreRipscanner_East,.,Wall_Steel,.,.</li>
				<li>Fence_Steel,.,Wall_Steel,.,.,.,.,.,.,.,.,.,.,.,.,.,.,Wall_Steel,.,Fence_Steel</li>
				<li>Fence_Steel,.,Wall_Steel,Wall_Steel,.,.,.,.,.,.,.,.,.,.,.,.,Wall_Steel,Wall_Steel,.,Fence_Steel</li>
				<li>Fence_Steel,.,StandingLamp,Wall_Steel,.,StandardRecharger_South,.,.,MechGestator_South,.,.,MechGestator_South,.,.,StandardRecharger_South,.,Wall_Steel,StandingLamp,.,Fence_Steel</li>
				<li>Fence_Steel,.,.,Wall_Steel,Wall_Steel,Wall_Steel,Wall_Steel,Wall_Steel,Wall_Steel,Wall_Steel,Wall_Steel,Wall_Steel,Wall_Steel,Wall_Steel,Wall_Steel,Wall_Steel,Wall_Steel,.,.,Fence_Steel</li>
				<li>Fence_Steel,Fence_Steel,.,.,.,.,.,.,.,.,.,.,.,.,.,.,.,.,Fence_Steel,Fence_Steel</li>
			</li>
			<li>
				<li>.,.,.,.,.,.,.,.,.,.,.,.,.,.,.,.,.,.,.,.</li>
				<li>.,.,.,PowerConduit,PowerConduit,PowerConduit,PowerConduit,PowerConduit,PowerConduit,.,.,PowerConduit,PowerConduit,PowerConduit,PowerConduit,PowerConduit,PowerConduit,.,.,.</li>
				<li>.,.,.,PowerConduit,.,.,.,.,PowerConduit,PowerConduit,PowerConduit,PowerConduit,.,.,.,.,PowerConduit,.,.,.</li>
				<li>.,.,.,PowerConduit,.,.,.,.,PowerConduit,.,.,PowerConduit,.,.,.,.,PowerConduit,.,.,.</li>
				<li>.,.,PowerConduit,PowerConduit,.,.,.,.,PowerConduit,.,.,PowerConduit,.,.,.,.,PowerConduit,PowerConduit,.,.</li>
				<li>.,.,PowerConduit,.,.,.,.,.,.,.,.,.,.,.,.,.,.,PowerConduit,.,.</li>
				<li>.,.,PowerConduit,.,.,.,.,.,.,.,.,.,.,.,.,.,.,PowerConduit,.,.</li>
				<li>.,PowerConduit,PowerConduit,.,.,.,.,.,.,.,.,.,.,.,.,.,.,PowerConduit,PowerConduit,.</li>
				<li>.,PowerConduit,.,.,.,.,.,.,.,.,.,.,.,.,.,.,.,.,PowerConduit,.</li>
				<li>.,PowerConduit,.,.,.,.,.,.,.,.,.,.,.,.,.,.,.,.,PowerConduit,.</li>
				<li>.,PowerConduit,.,.,.,.,.,.,.,.,.,.,.,.,.,.,.,.,PowerConduit,.</li>
				<li>.,PowerConduit,PowerConduit,.,.,.,.,.,.,.,.,.,.,.,.,.,.,PowerConduit,PowerConduit,.</li>
				<li>.,.,PowerConduit,.,.,.,.,.,.,.,.,.,.,.,.,.,.,PowerConduit,.,.</li>
				<li>.,.,PowerConduit,.,.,.,.,.,.,.,.,.,.,.,.,.,.,PowerConduit,.,.</li>
				<li>.,.,PowerConduit,PowerConduit,.,.,.,.,.,.,.,.,.,.,.,.,PowerConduit,PowerConduit,.,.</li>
				<li>.,.,.,PowerConduit,.,.,.,.,.,.,.,.,.,.,.,.,PowerConduit,.,.,.</li>
				<li>.,.,.,PowerConduit,PowerConduit,PowerConduit,PowerConduit,PowerConduit,PowerConduit,PowerConduit,PowerConduit,PowerConduit,PowerConduit,PowerConduit,PowerConduit,PowerConduit,PowerConduit,.,.,.</li>
				<li>.,.,.,.,.,.,.,.,.,.,.,.,.,.,.,.,.,.,.,.</li>
			</li>
		</layouts>
		<roofGrid>
			<li>.,.,.,.,.,.,.,.,.,.,.,.,.,.,.,.,.,.,.,.</li>
			<li>.,.,.,1,1,1,1,1,1,1,1,1,1,1,1,1,1,.,.,.</li>
			<li>.,.,.,1,1,1,1,1,1,1,1,1,1,1,1,1,1,.,.,.</li>
			<li>.,.,.,1,1,1,1,1,1,1,1,1,1,1,1,1,1,.,.,.</li>
			<li>.,.,1,1,1,1,1,1,1,1,1,1,1,1,1,1,1,1,.,.</li>
			<li>.,.,1,1,1,1,1,1,1,1,1,1,1,1,1,1,1,1,.,.</li>
			<li>.,.,1,1,1,1,1,1,1,1,1,1,1,1,1,1,1,1,.,.</li>
			<li>.,1,1,1,1,1,1,1,1,1,1,1,1,1,1,1,1,1,1,.</li>
			<li>.,1,1,1,1,1,1,1,1,1,1,1,1,1,1,1,1,1,1,.</li>
			<li>.,1,1,1,1,1,1,1,1,1,1,1,1,1,1,1,1,1,1,.</li>
			<li>.,1,1,1,1,1,1,1,1,1,1,1,1,1,1,1,1,1,1,.</li>
			<li>.,1,1,1,1,1,1,1,1,1,1,1,1,1,1,1,1,1,1,.</li>
			<li>.,.,1,1,1,1,1,1,1,1,1,1,1,1,1,1,1,1,.,.</li>
			<li>.,.,1,1,1,1,1,1,1,1,1,1,1,1,1,1,1,1,.,.</li>
			<li>.,.,1,1,1,1,1,1,1,1,1,1,1,1,1,1,1,1,.,.</li>
			<li>.,.,.,1,1,1,1,1,1,1,1,1,1,1,1,1,1,.,.,.</li>
			<li>.,.,.,1,1,1,1,1,1,1,1,1,1,1,1,1,1,.,.,.</li>
			<li>.,.,.,.,.,.,.,.,.,.,.,.,.,.,.,.,.,.,.,.</li>
		</roofGrid>
		<terrainGrid>
			<li>PavedTile,PavedTile,PavedTile,PavedTile,PavedTile,PavedTile,PavedTile,PavedTile,PavedTile,PavedTile,PavedTile,PavedTile,PavedTile,PavedTile,PavedTile,PavedTile,PavedTile,PavedTile,PavedTile,PavedTile</li>
			<li>PavedTile,PavedTile,PavedTile,.,.,.,.,.,.,PavedTile,PavedTile,.,.,.,.,.,.,PavedTile,PavedTile,PavedTile</li>
			<li>PavedTile,PavedTile,PavedTile,.,PavedTile,PavedTile,PavedTile,PavedTile,.,MetalTile,MetalTile,.,PavedTile,PavedTile,PavedTile,PavedTile,.,PavedTile,PavedTile,PavedTile</li>
			<li>PavedTile,PavedTile,PavedTile,.,PavedTile,PavedTile,PavedTile,PavedTile,.,MetalTile,MetalTile,.,PavedTile,PavedTile,PavedTile,PavedTile,.,PavedTile,PavedTile,PavedTile</li>
			<li>PavedTile,PavedTile,.,.,PavedTile,PavedTile,PavedTile,PavedTile,.,MetalTile,MetalTile,.,PavedTile,PavedTile,PavedTile,PavedTile,.,.,PavedTile,PavedTile</li>
			<li>PavedTile,PavedTile,.,PavedTile,PavedTile,PavedTile,PavedTile,PavedTile,PavedTile,MetalTile,MetalTile,PavedTile,PavedTile,PavedTile,PavedTile,PavedTile,PavedTile,.,PavedTile,PavedTile</li>
			<li>PavedTile,PavedTile,.,PavedTile,PavedTile,MetalTile,MetalTile,MetalTile,MetalTile,MetalTile,MetalTile,MetalTile,MetalTile,MetalTile,MetalTile,PavedTile,PavedTile,.,PavedTile,PavedTile</li>
			<li>PavedTile,.,.,PavedTile,PavedTile,MetalTile,MetalTile,MetalTile,MetalTile,MetalTile,MetalTile,MetalTile,MetalTile,MetalTile,MetalTile,PavedTile,PavedTile,.,.,PavedTile</li>
			<li>PavedTile,.,PavedTile,PavedTile,PavedTile,MetalTile,MetalTile,MetalTile,MetalTile,MetalTile,MetalTile,MetalTile,MetalTile,MetalTile,MetalTile,PavedTile,PavedTile,PavedTile,.,PavedTile</li>
			<li>PavedTile,.,PavedTile,PavedTile,PavedTile,MetalTile,MetalTile,MetalTile,MetalTile,MetalTile,MetalTile,MetalTile,MetalTile,MetalTile,MetalTile,PavedTile,PavedTile,PavedTile,.,PavedTile</li>
			<li>PavedTile,.,PavedTile,PavedTile,PavedTile,MetalTile,MetalTile,MetalTile,MetalTile,MetalTile,MetalTile,MetalTile,MetalTile,MetalTile,MetalTile,PavedTile,PavedTile,PavedTile,.,PavedTile</li>
			<li>PavedTile,.,.,PavedTile,PavedTile,MetalTile,MetalTile,MetalTile,MetalTile,MetalTile,MetalTile,MetalTile,MetalTile,MetalTile,MetalTile,PavedTile,PavedTile,.,.,PavedTile</li>
			<li>PavedTile,PavedTile,PavedTile,PavedTile,PavedTile,MetalTile,MetalTile,MetalTile,MetalTile,MetalTile,MetalTile,MetalTile,MetalTile,MetalTile,MetalTile,PavedTile,PavedTile,PavedTile,PavedTile,PavedTile</li>
			<li>PavedTile,PavedTile,PavedTile,PavedTile,PavedTile,PavedTile,PavedTile,PavedTile,PavedTile,PavedTile,PavedTile,PavedTile,PavedTile,PavedTile,PavedTile,PavedTile,PavedTile,PavedTile,PavedTile,PavedTile</li>
			<li>PavedTile,PavedTile,PavedTile,PavedTile,PavedTile,PavedTile,PavedTile,PavedTile,PavedTile,PavedTile,PavedTile,PavedTile,PavedTile,PavedTile,PavedTile,PavedTile,PavedTile,PavedTile,PavedTile,PavedTile</li>
			<li>PavedTile,PavedTile,PavedTile,PavedTile,PavedTile,PavedTile,PavedTile,PavedTile,PavedTile,PavedTile,PavedTile,PavedTile,PavedTile,PavedTile,PavedTile,PavedTile,PavedTile,PavedTile,PavedTile,PavedTile</li>
			<li>PavedTile,PavedTile,PavedTile,.,.,PavedTile,.,.,.,.,.,.,.,.,PavedTile,.,.,PavedTile,PavedTile,PavedTile</li>
			<li>PavedTile,PavedTile,PavedTile,PavedTile,PavedTile,PavedTile,PavedTile,PavedTile,PavedTile,PavedTile,PavedTile,PavedTile,PavedTile,PavedTile,PavedTile,PavedTile,PavedTile,PavedTile,PavedTile,PavedTile</li>
		</terrainGrid>
		<modRequirements>
			<li>ludeon.rimworld.biotech</li>
		</modRequirements>
	</KCSG.StructureLayoutDef>
	<KCSG.StructureLayoutDef>
		<defName>AP_Prefab_Production_GeneticsLab</defName>
		<spawnConduits>false</spawnConduits>
		<layouts>
			<li>
				<li>.,.,.,.,.,.,.,.,.,.,.,.,.,.,.</li>
				<li>.,.,.,.,StandingLamp,Wall_Steel,Wall_Steel,Autodoor_Steel,Wall_Steel,Wall_Steel,StandingLamp,.,.,.,.</li>
				<li>.,.,.,Wall_Steel,Wall_Steel,Wall_Steel,.,.,.,Wall_Steel,Wall_Steel,Wall_Steel,.,.,.</li>
				<li>.,.,.,Wall_Steel,GeneProcessor,.,GrowthVat_South,.,GrowthVat_South,MultiAnalyzer,.,Wall_Steel,.,.,.</li>
				<li>.,Wall_Steel,Wall_Steel,Wall_Steel,.,.,.,.,.,.,.,Wall_Steel,Wall_Steel,Wall_Steel,.</li>
				<li>.,Wall_Steel,GeneBank_North,.,.,.,.,.,.,.,Battery_North,PowerConduit,.,Wall_Steel,.</li>
				<li>.,Wall_Steel,GeneBank_North,.,.,.,.,.,.,.,.,.,.,Wall_Steel,.</li>
				<li>.,Wall_Steel,GeneBank_North,.,.,.,GeneExtractor_South,.,GeneExtractor_South,.,PowerConduit,HiTechResearchBench_Steel_East,.,Wall_Steel,.</li>
				<li>.,Wall_Steel,GeneBank_North,.,.,StandingLamp,Battery_East,.,StandingLamp,PowerConduit,Battery_North,.,.,Wall_Steel,.</li>
				<li>.,Wall_Steel,GeneBank_North,.,.,.,.,.,.,.,.,PowerConduit,.,Wall_Steel,.</li>
				<li>.,Wall_Steel,Wall_Steel,Wall_Steel,GeneProcessor,.,.,.,.,GeneProcessor,.,Wall_Steel,Wall_Steel,Wall_Steel,.</li>
				<li>.,.,StandingLamp,Wall_Steel,.,.,.,GeneAssembler_South,.,.,.,Wall_Steel,StandingLamp,.,.</li>
				<li>.,.,.,Wall_Steel,Wall_Steel,Wall_Steel,Wall_Steel,Wall_Steel,Wall_Steel,Wall_Steel,Wall_Steel,Wall_Steel,.,.,.</li>
				<li>.,.,.,.,.,.,.,.,.,.,.,.,.,.,.</li>
			</li>
			<li>
				<li>.,.,.,.,.,.,.,.,.,.,.,.,.,.,.</li>
				<li>.,.,.,.,.,PowerConduit,PowerConduit,PowerConduit,PowerConduit,PowerConduit,.,.,.,.,.</li>
				<li>.,.,.,PowerConduit,PowerConduit,PowerConduit,.,.,.,PowerConduit,PowerConduit,PowerConduit,.,.,.</li>
				<li>.,.,.,PowerConduit,.,.,.,.,.,.,.,PowerConduit,.,.,.</li>
				<li>.,PowerConduit,PowerConduit,PowerConduit,.,.,.,.,.,.,.,PowerConduit,PowerConduit,PowerConduit,.</li>
				<li>.,PowerConduit,.,.,.,.,.,.,.,.,.,.,.,PowerConduit,.</li>
				<li>.,PowerConduit,.,.,.,.,.,.,.,.,.,.,.,PowerConduit,.</li>
				<li>.,PowerConduit,.,.,.,.,.,.,.,.,DiningChair_WoodLog_East,.,.,PowerConduit,.</li>
				<li>.,PowerConduit,.,.,.,.,.,.,PowerConduit,.,.,.,.,PowerConduit,.</li>
				<li>.,PowerConduit,.,.,.,.,.,.,.,.,.,.,.,PowerConduit,.</li>
				<li>.,PowerConduit,PowerConduit,PowerConduit,.,.,.,.,.,.,.,PowerConduit,PowerConduit,PowerConduit,.</li>
				<li>.,.,.,PowerConduit,.,.,.,.,.,.,.,PowerConduit,.,.,.</li>
				<li>.,.,.,PowerConduit,PowerConduit,PowerConduit,PowerConduit,PowerConduit,PowerConduit,PowerConduit,PowerConduit,PowerConduit,.,.,.</li>
				<li>.,.,.,.,.,.,.,.,.,.,.,.,.,.,.</li>
			</li>
		</layouts>
		<roofGrid>
			<li>.,.,.,.,.,.,.,.,.,.,.,.,.,.,.</li>
			<li>.,.,.,.,.,1,1,1,1,1,.,.,.,.,.</li>
			<li>.,.,.,1,1,1,1,1,1,1,1,1,.,.,.</li>
			<li>.,.,.,1,1,1,1,1,1,1,1,1,.,.,.</li>
			<li>.,1,1,1,1,1,1,1,1,1,1,1,1,1,.</li>
			<li>.,1,1,1,1,1,1,1,1,1,1,1,1,1,.</li>
			<li>.,1,1,1,1,1,1,1,1,1,1,1,1,1,.</li>
			<li>.,1,1,1,1,1,1,1,1,1,1,1,1,1,.</li>
			<li>.,1,1,1,1,1,1,1,1,1,1,1,1,1,.</li>
			<li>.,1,1,1,1,1,1,1,1,1,1,1,1,1,.</li>
			<li>.,1,1,1,1,1,1,1,1,1,1,1,1,1,.</li>
			<li>.,.,.,1,1,1,1,1,1,1,1,1,.,.,.</li>
			<li>.,.,.,1,1,1,1,1,1,1,1,1,.,.,.</li>
			<li>.,.,.,.,.,.,.,.,.,.,.,.,.,.,.</li>
		</roofGrid>
		<terrainGrid>
			<li>.,.,.,PavedTile,PavedTile,PavedTile,PavedTile,PavedTile,PavedTile,PavedTile,PavedTile,PavedTile,.,.,.</li>
			<li>.,.,PavedTile,PavedTile,PavedTile,.,.,SterileTile,.,.,PavedTile,PavedTile,PavedTile,.,.</li>
			<li>.,.,PavedTile,.,.,.,SterileTile,SterileTile,SterileTile,.,.,.,PavedTile,.,.</li>
			<li>PavedTile,PavedTile,PavedTile,.,SterileTile,SterileTile,SterileTile,SterileTile,SterileTile,SterileTile,SterileTile,.,PavedTile,PavedTile,PavedTile</li>
			<li>PavedTile,PavedTile,.,.,SterileTile,SterileTile,SterileTile,SterileTile,SterileTile,SterileTile,SterileTile,.,.,PavedTile,PavedTile</li>
			<li>PavedTile,PavedTile,SterileTile,SterileTile,SterileTile,SterileTile,SterileTile,SterileTile,SterileTile,SterileTile,SterileTile,SterileTile,SterileTile,PavedTile,PavedTile</li>
			<li>PavedTile,PavedTile,SterileTile,SterileTile,SterileTile,SterileTile,SterileTile,SterileTile,SterileTile,SterileTile,SterileTile,SterileTile,SterileTile,PavedTile,PavedTile</li>
			<li>PavedTile,PavedTile,SterileTile,SterileTile,SterileTile,SterileTile,SterileTile,SterileTile,SterileTile,SterileTile,SterileTile,SterileTile,SterileTile,PavedTile,PavedTile</li>
			<li>PavedTile,PavedTile,SterileTile,SterileTile,SterileTile,SterileTile,SterileTile,SterileTile,SterileTile,SterileTile,SterileTile,SterileTile,SterileTile,PavedTile,PavedTile</li>
			<li>PavedTile,PavedTile,SterileTile,SterileTile,SterileTile,SterileTile,SterileTile,SterileTile,SterileTile,SterileTile,SterileTile,SterileTile,SterileTile,PavedTile,PavedTile</li>
			<li>PavedTile,PavedTile,.,.,SterileTile,SterileTile,SterileTile,SterileTile,SterileTile,SterileTile,SterileTile,.,.,PavedTile,PavedTile</li>
			<li>PavedTile,PavedTile,PavedTile,.,SterileTile,SterileTile,SterileTile,SterileTile,SterileTile,SterileTile,SterileTile,.,PavedTile,PavedTile,PavedTile</li>
			<li>.,PavedTile,PavedTile,PavedTile,PavedTile,.,.,.,.,.,PavedTile,PavedTile,PavedTile,PavedTile,.</li>
			<li>.,.,PavedTile,PavedTile,PavedTile,PavedTile,PavedTile,PavedTile,PavedTile,PavedTile,PavedTile,PavedTile,PavedTile,.,.</li>
		</terrainGrid>
		<modRequirements>
			<li>ludeon.rimworld.biotech</li>
		</modRequirements>
	</KCSG.StructureLayoutDef>
	<KCSG.StructureLayoutDef>
  <defName>AP_Prefab_WarcasketFoundry</defName>
  <spawnConduits>false</spawnConduits>
  <layouts>
    <li>
      <li>Plant_Berry,Wall_BlocksGranite,Wall_BlocksGranite,Wall_BlocksGranite,Wall_BlocksGranite,Door_WoodLog,Wall_BlocksGranite,Wall_BlocksGranite,Wall_BlocksGranite,Wall_BlocksGranite,.</li>
      <li>Wall_BlocksGranite,Wall_BlocksGranite,.,.,.,.,.,.,.,Wall_BlocksGranite,Wall_BlocksGranite</li>
      <li>Wall_BlocksGranite,.,Shelf_WoodLog_South,.,Shelf_WoodLog_South,.,.,Shelf_WoodLog_South,.,Shelf_WoodLog_South,Wall_BlocksGranite</li>
      <li>Wall_BlocksGranite,.,.,.,.,.,.,.,.,.,Wall_BlocksGranite</li>
      <li>Wall_BlocksGranite,.,Shelf_WoodLog_South,.,Shelf_WoodLog_South,.,.,Shelf_WoodLog_South,.,Shelf_WoodLog_South,Wall_BlocksGranite</li>
      <li>Wall_BlocksGranite,.,.,.,.,.,.,.,.,.,Wall_BlocksGranite</li>
      <li>Wall_BlocksGranite,.,Shelf_WoodLog_South,.,Shelf_WoodLog_South,.,.,Shelf_WoodLog_South,.,Shelf_WoodLog_South,Wall_BlocksGranite</li>
      <li>Wall_BlocksGranite,Wall_BlocksGranite,StandingLamp,.,.,.,.,.,StandingLamp,Wall_BlocksGranite,Wall_BlocksGranite</li>
      <li>.,Wall_BlocksGranite,VFEPD_SpacerContainer_South,.,.,.,.,.,VFEP_Box_Autorifle,Wall_BlocksGranite,.</li>
      <li>.,Wall_BlocksGranite,VFEPD_SpacerContainer_South,.,.,.,.,.,VFEP_Box_Autorifle,Wall_BlocksGranite,.</li>
      <li>Wall_BlocksGranite,Wall_BlocksGranite,VFES_AmmoCrate,.,.,VFEP_WarcasketFoundry,.,.,VFEP_Box_Slugthrower,Wall_BlocksGranite,Wall_BlocksGranite</li>
      <li>Wall_BlocksGranite,.,.,.,.,.,.,.,.,.,Wall_BlocksGranite</li>
      <li>Wall_BlocksGranite,TableMachining_West,DiningChair_Steel_West,.,.,.,.,.,DiningChair_Steel_East,ElectricSmithy_East,Wall_BlocksGranite</li>
      <li>Wall_BlocksGranite,.,StandingLamp,.,.,DiningChair_Steel_North,.,.,StandingLamp,.,Wall_BlocksGranite</li>
      <li>Wall_BlocksGranite,ToolCabinet_North,.,.,.,FabricationBench_North,.,.,ToolCabinet_North,.,Wall_BlocksGranite</li>
      <li>Wall_BlocksGranite,Wall_BlocksGranite,Wall_BlocksGranite,.,.,.,.,.,Wall_BlocksGranite,Wall_BlocksGranite,Wall_BlocksGranite</li>
      <li>.,.,Wall_BlocksGranite,Wall_BlocksGranite,Wall_BlocksGranite,Wall_BlocksGranite,Wall_BlocksGranite,Wall_BlocksGranite,Wall_BlocksGranite,.,.</li>
    </li>
    <li>
      <li>.,PowerConduit,PowerConduit,PowerConduit,PowerConduit,PowerConduit,PowerConduit,PowerConduit,PowerConduit,PowerConduit,.</li>
      <li>PowerConduit,PowerConduit,.,.,.,.,.,.,.,PowerConduit,PowerConduit</li>
      <li>PowerConduit,.,.,.,Steel,.,Plasteel,.,.,Steel,PowerConduit</li>
      <li>PowerConduit,.,.,.,.,.,.,.,.,.,PowerConduit</li>
      <li>PowerConduit,.,Steel,.,.,.,.,Steel,.,.,PowerConduit</li>
      <li>PowerConduit,.,.,.,.,.,.,.,.,.,PowerConduit</li>
      <li>PowerConduit,.,Plasteel,.,Steel,.,.,.,.,Steel,PowerConduit</li>
      <li>PowerConduit,PowerConduit,.,.,.,.,.,.,.,PowerConduit,PowerConduit</li>
      <li>.,PowerConduit,.,.,.,.,.,.,.,PowerConduit,.</li>
      <li>.,PowerConduit,.,.,.,.,.,.,.,PowerConduit,.</li>
      <li>PowerConduit,PowerConduit,.,.,.,.,.,.,.,PowerConduit,PowerConduit</li>
      <li>PowerConduit,.,.,.,.,.,.,.,.,.,PowerConduit</li>
      <li>PowerConduit,.,.,.,.,.,.,.,.,.,PowerConduit</li>
      <li>PowerConduit,.,.,.,.,.,.,.,.,.,PowerConduit</li>
      <li>PowerConduit,.,.,.,.,.,.,.,.,.,PowerConduit</li>
      <li>PowerConduit,PowerConduit,PowerConduit,.,.,.,.,.,PowerConduit,PowerConduit,PowerConduit</li>
      <li>.,.,PowerConduit,PowerConduit,PowerConduit,PowerConduit,PowerConduit,PowerConduit,PowerConduit,.,.</li>
    </li>
  </layouts>
  <roofGrid>
    <li>.,1,1,1,1,1,1,1,1,1,.</li>
    <li>1,1,1,1,1,1,1,1,1,1,1</li>
    <li>1,1,1,1,1,1,1,1,1,1,1</li>
    <li>1,1,1,1,1,1,1,1,1,1,1</li>
    <li>1,1,1,1,1,1,1,1,1,1,1</li>
    <li>1,1,1,1,1,1,1,1,1,1,1</li>
    <li>1,1,1,1,1,1,1,1,1,1,1</li>
    <li>1,1,1,1,1,1,1,1,1,1,1</li>
    <li>.,1,1,1,1,1,1,1,1,1,.</li>
    <li>.,1,1,1,1,1,1,1,1,1,.</li>
    <li>1,1,1,1,1,1,1,1,1,1,1</li>
    <li>1,1,1,1,1,1,1,1,1,1,1</li>
    <li>1,1,1,1,1,1,1,1,1,1,1</li>
    <li>1,1,1,1,1,1,1,1,1,1,1</li>
    <li>1,1,1,1,1,1,1,1,1,1,1</li>
    <li>1,1,1,1,1,1,1,1,1,1,1</li>
    <li>.,.,1,1,1,1,1,1,1,.,.</li>
  </roofGrid>
  <terrainGrid>
    <li>.,.,.,.,.,PavedTile,.,.,.,.,.</li>
    <li>.,.,MetalTile,MetalTile,MetalTile,MetalTile,MetalTile,MetalTile,MetalTile,.,.</li>
    <li>.,PavedTile,PavedTile,PavedTile,PavedTile,MetalTile,PavedTile,PavedTile,PavedTile,PavedTile,.</li>
    <li>.,MetalTile,MetalTile,MetalTile,MetalTile,MetalTile,MetalTile,MetalTile,MetalTile,MetalTile,.</li>
    <li>.,PavedTile,PavedTile,PavedTile,PavedTile,MetalTile,PavedTile,PavedTile,PavedTile,PavedTile,.</li>
    <li>.,MetalTile,MetalTile,MetalTile,MetalTile,MetalTile,MetalTile,MetalTile,MetalTile,MetalTile,.</li>
    <li>.,PavedTile,PavedTile,PavedTile,PavedTile,MetalTile,PavedTile,PavedTile,PavedTile,PavedTile,.</li>
    <li>.,PavedTile,PavedTile,PavedTile,PavedTile,MetalTile,PavedTile,PavedTile,PavedTile,PavedTile,.</li>
    <li>.,PavedTile,PavedTile,MetalTile,MetalTile,MetalTile,MetalTile,MetalTile,PavedTile,PavedTile,.</li>
    <li>.,PavedTile,PavedTile,MetalTile,Concrete,Concrete,Concrete,MetalTile,PavedTile,PavedTile,.</li>
    <li>.,PavedTile,PavedTile,MetalTile,Concrete,Concrete,Concrete,MetalTile,PavedTile,PavedTile,.</li>
    <li>.,PavedTile,PavedTile,MetalTile,Concrete,Concrete,Concrete,MetalTile,PavedTile,PavedTile,.</li>
    <li>.,PavedTile,PavedTile,MetalTile,MetalTile,MetalTile,MetalTile,MetalTile,PavedTile,PavedTile,.</li>
    <li>.,PavedTile,PavedTile,PavedTile,PavedTile,PavedTile,PavedTile,PavedTile,PavedTile,PavedTile,.</li>
    <li>.,PavedTile,PavedTile,PavedTile,PavedTile,PavedTile,PavedTile,PavedTile,PavedTile,PavedTile,.</li>
    <li>.,.,.,PavedTile,PavedTile,PavedTile,PavedTile,PavedTile,.,.,.</li>
    <li>.,.,.,.,.,.,.,.,.,.,.</li>
  </terrainGrid>
  <modRequirements>
    <li>oskarpotocki.vfe.pirates</li>
    <li>vanillaexpanded.vfepropsanddecor</li>
    <li>vanillaexpanded.vfesecurity</li>
  </modRequirements>
</KCSG.StructureLayoutDef>
</Defs>